Workbook

Sheet Index
A1: Index
A2: 1 | B2: IS
A3: 2 | B3: BS
A4: 3 | B4: IS_XLOOKUP
A5: 4 | B5: ISCOMP
A6: 5 | B6: BS_XLOOP
A7: 6 | B7: BSCOMP
A8: 7 | B8: ISCOMM
A9: 8 | B9: BSCOMM

Sheet IS
A1: Income Statement of Tata Motors from FY2020 TO FY2024
A2: Particulars | B2: FY2024 | C2: FY2023 | D2: FY2022 | E2: FY2021 | F2: FY2020
A3: I. Revenue from operations
A4: (a) Revenue | B4: 72745.92 | C4: 65298.84 | D4: 46880.97 | E4: 46559.39 | F4: 43485.76
A5: (b) Other operating revenue | B5: 557.16 | C5: 458.49 | D5: 382.71 | E5: 472.08 | F5: 442.41
A6: Total revenue from operations (I) | B6: 73303.08 | C6: 65757.33 | D6: 47263.68 | E6: 47031.47 | F6: 43928.17
A7: II. Other Income | B7: 1149.88 | C7: 820.94 | D7: 659.91 | E7: 842.96 | F7: 1383.05
A8: III. Total Income (I+II) | B8: 74452.96 | C8: 66578.27 | D8: 47923.59 | E8: 47874.43 | F8: 45311.22
A9: IV. Expenses:
A10: (a) Cost of materials consumed | B10: 46757.28 | C10: 42226.81 | D10: 31693.11 | E10: 28493.12 | F10: 26171.85
A11: (b) Purchases of products for sale | B11: 6707.03 | C11: 6561.32 | D11: 5030 | E11: 7518.05 | F11: 5679.98
A12: (c) Changes in Stock | B12: 1736.35 | C12: 484.69 | D12: -403.87 | E12: -108.48 | F12: 722.68
A13: (d) Employee benefits expense | B13: 4308.15 | C13: 4021.63 | D13: 3601.51 | E13: 3987.72 | F13: 4384.31
A14: (e) Finance costs | B14: 1705.74 | C14: 2047.51 | D14: 2121.73 | E14: 2288.61 | F14: 1973
A15: (f) Foreign exchange loss (net) | B15: 200.72 | C15: 279.76 | D15: 136.81 | E15: 29.02 | F15: 239
A16: (g) Depreciation and amortisation expense | B16: 2016.84 | C16: 1766.86 | D16: 1760.57 | E16: 3325.8 | F16: 3375.29
A17: (h) Product development/Engineering expenses | B17: 1104.79 | C17: 899.06 | D17: 593.9 | E17: 907.44 | F17: 830.24
A18: (i) Other expenses | B18: 7610.15 | C18: 7819.74 | D18: 6018.71 | E18: 5612.48 | F18: 7720.75
A19: (j) Amount transferred to capital and other accounts | B19: -1129.73 | C19: -1066.73 | D19: -905.42 | E19: -817.53 | F19: -1169.46
A20: Total Expenses (IV) | B20: 69317.32 | C20: 65040.65 | D20: 49647.05 | E20: 51239.38 | F20: 49927.64
A21: V. Profit/(Loss) before exceptional items and tax (III-IV) | B21: 5135.64 | C21: 1537.62 | D21: -1723.46 | E21: -3364.95 | F21: -4616.42
... A27: XI. Total comprehensive income/(loss) for the year | B27: 8338.64 | C27: 2451.64 | D27: -1267.18 | E27: -1952.45 | F27: -7668.35

Sheet BS
A1: Balance Sheet of Tata Motors from FY2020 TO FY2024
A2: Particulars | B2: FY2024 | C2: FY2023 | D2: FY2022 | E2: FY2021 | F2: FY2020
A3: I. ASSETS
A4: (1) NON-CURRENT ASSETS | B4: 36133.09 | C4: 33060.22 | D4: 30958.82 | E4: 30283.65 | F4: 47242.06
A5: Property, plant and equipment (PPE) | B5: 12056.24 | C5: 12176.6 | D5: 11811.02 | E5: 17143.04 | F5: 18870.67
A6: Capital work-in-progress (CWIP) | B6: 575.65 | C6: 575.65 | D6: 585.21 | E6: 1324.21 | F6: 1755.51
A7: Right of use assets (ROU) | B7: 338.25 | C7: 344.2 | D7: 332.45 | E7: 979.48 | F7: 669.58
A8: Goodwill | B8: 99.09 | C8: 99.09 | D8: 99.09 | E8: 99.09 | F8: 99.09
A9: Other intangible assets | B9: 1768.49 | C9: 1914.76 | D9: 2009.87 | E9: 6156.56 | F9: 5568.64
A10: Intangible assets under development | B10: 509.3 | C10: 509.3 | D10: 882.03 | E10: 1604.23 | F10: 2739.29
A11: Investments in subsidiaries, JVs & associates | B11: 25819.34 | C11: 27976.8 | D11: 24723.34 | E11: 14287.8 | F11: 15182.29
A12: Financial assets (Investments, Loans, Others) | B12: -1283.47 | C12: -1402.16 | D12: -1507.57 | E12: 1691.01 | F12: 2204.53
A13: Non-current tax assets (Net) | B13: 1751.48 | C13: 1909.8 | D13: 1847.16 | E13: 741.02 | F13: 727.97
A14: Other non-current assets | B14: -1301.98 | C14: -1439.42 | D14: -2059.45 | E14: 1056.77 | F14: 1208.08
A15: (2) CURRENT ASSETS | B15: 36258.71 | C15: 26868.97 | D15: 26792.13 | E15: 25309.78 | F15: 7861.82
... A20: TOTAL ASSETS (1) + (2) | B20: 72391.8 | C20: 59929.19 | D20: 57750.95 | E20: 55593.43 | F20: 55103.88
A22: II. EQUITY AND LIABILITIES
A23: (1) EQUITY | B23: 34068.79 | C23: 28683.65 | D23: 27786.17 | E23: 27173.34 | F23: 24545.91
A24: Equity share capital | B24: 766.49 | C24: 766.02 | D24: 765.88 | E24: 765.81 | F24: 719.54
A25: Other equity | B25: 33302.3 | C25: 27917.63 | D25: 27020.29 | E25: 26407.53 | F25: 23826.37
A26: (2) NON-CURRENT LIABILITIES | B26: 14449.18 | C26: 10501.71 | D26: 9436.56 | E26: 10544.75 | F26: 13293.48
A27: Financial liabilities (Borrowings & Lease) | B27: 11632.4 | C27: 7654.51 | D27: 6560.85 | E27: 7728.84 | F27: 10234.34
A28: Provisions | B28: 2752.48 | C28: 2787.05 | D28: 2828.53 | E28: 2776.99 | F28: 3030.14
A29: Deferred tax liabilities (Net) | B29: -7.8 | C29: 1.83 | D29: 1.84 | E29: -373.19 | F29: 7.92
A30: Other non-current liabilities | B30: 72.1 | C30: 58.32 | D30: 45.34 | E30: 412 | F30: 21.08
A31: (3) CURRENT LIABILITIES | B31: 23873.83 | C31: 20743.83 | D31: 20528.22 | E31: 17875.34 | F31: 17264.49
A32: Financial liabilities (Borrowings, Trade Payables, Others) | B32: 22234.33 | C32: 18973.91 | D32: 18913.34 | E32: 16339.06 | F32: 15360.7
A33: Provisions | B33: 1023.7 | C33: 1087.49 | D33: 913.04 | E33: 910.16 | F33: 1043.54
A34: Current tax liabilities (Net) | B34: 148.16 | C34: 212.72 | D34: 19.82 | E34: 87.05 | F34: 295.34
... A36: TOTAL EQUITY AND LIABILITIES (1) + (2) + (3) | B36: 72391.8 | C36: 59929.19 | D36: 57750.95 | E36: 55593.43 | F36: 55103.88

Sheet IS_XLOOKUP
A1: Comparative Income Statement of Tata Motors from FY2020 TO FY2024
A2: Particulars | B2: FY2024 | C2: FY2023 | D2: FY2022 | E2: FY2021 | F2: FY2020
A3: I. Revenue from operations
A4: (a) Revenue | B4: =_xlfn.XLOOKUP($A4,IS!$A$2:$A$27,IS!B$2:B$27," ",0,1) -> 72745.92 | C4: =_xlfn.XLOOKUP($A4,IS!$A$2:$A$27,IS!C$2:C$27," ",0,1) -> 65298.84 | D4: =_xlfn.XLOOKUP($A4,IS!$A$2:$A$27,IS!D$2:D$27," ",0,1) -> 46880.97 | E4: =_xlfn.XLOOKUP($A4,IS!$A$2:$A$27,IS!E$2:E$27," ",0,1) -> 46559.39 | F4: =_xlfn.XLOOKUP($A4,IS!$A$2:$A$27,IS!F$2:F$27," ",0,1) -> 43485.76
A5: (b) Other operating revenue | B5: =_xlfn.XLOOKUP($A5,IS!$A$2:$A$27,IS!B$2:B$27," ",0,1) -> 557.16 | C5: =_xlfn.XLOOKUP($A5,IS!$A$2:$A$27,IS!C$2:C$27," ",0,1) -> 458.49 | D5: =_xlfn.XLOOKUP($A5,IS!$A$2:$A$27,IS!D$2:D$27," ",0,1) -> 382.71 | E5: =_xlfn.XLOOKUP($A5,IS!$A$2:$A$27,IS!E$2:E$27," ",0,1) -> 472.08 | F5: =_xlfn.XLOOKUP($A5,IS!$A$2:$A$27,IS!F$2:F$27," ",0,1) -> 442.41
A6: Total revenue from operations (I) | B6: =_xlfn.XLOOKUP($A6,IS!$A$2:$A$27,IS!B$2:B$27," ",0,1) -> 73303.08 | C6: =_xlfn.XLOOKUP($A6,IS!$A$2:$A$27,IS!C$2:C$27," ",0,1) -> 65757.33 | D6: =_xlfn.XLOOKUP($A6,IS!$A$2:$A$27,IS!D$2:D$27," ",0,1) -> 47263.68 | E6: =_xlfn.XLOOKUP($A6,IS!$A$2:$A$27,IS!E$2:E$27," ",0,1) -> 47031.47 | F6: =_xlfn.XLOOKUP($A6,IS!$A$2:$A$27,IS!F$2:F$27," ",0,1) -> 43928.17
A7: II. Other Income | B7: =_xlfn.XLOOKUP($A7,IS!$A$2:$A$27,IS!B$2:B$27," ",0,1) -> 1149.88 | C7: =_xlfn.XLOOKUP($A7,IS!$A$2:$A$27,IS!C$2:C$27," ",0,1) -> 820.94 | D7: =_xlfn.XLOOKUP($A7,IS!$A$2:$A$27,IS!D$2:D$27," ",0,1) -> 659.91 | E7: =_xlfn.XLOOKUP($A7,IS!$A$2:$A$27,IS!E$2:E$27," ",0,1) -> 842.96 | F7: =_xlfn.XLOOKUP($A7,IS!$A$2:$A$27,IS!F$2:F$27," ",0,1) -> 1383.05
A8: III. Total Income (I+II) | B8: =_xlfn.XLOOKUP($A8,IS!$A$2:$A$27,IS!B$2:B$27," ",0,1) -> 74452.96 | C8: =_xlfn.XLOOKUP($A8,IS!$A$2:$A$27,IS!C$2:C$27," ",0,1) -> 66578.27 | D8: =_xlfn.XLOOKUP($A8,IS!$A$2:$A$27,IS!D$2:D$27," ",0,1) -> 47923.59 | E8: =_xlfn.XLOOKUP($A8,IS!$A$2:$A$27,IS!E$2:E$27," ",0,1) -> 47874.43 | F8: =_xlfn.XLOOKUP($A8,IS!$A$2:$A$27,IS!F$2:F$27," ",0,1) -> 45311.22
A9: IV. Expenses:
A10: (a) Cost of materials consumed | B10: =_xlfn.XLOOKUP($A10,IS!$A$2:$A$27,IS!B$2:B$27," ",0,1) -> 46757.28 | C10: =_xlfn.XLOOKUP($A10,IS!$A$2:$A$27,IS!C$2:C$27," ",0,1) -> 42226.81 | D10: =_xlfn.XLOOKUP($A10,IS!$A$2:$A$27,IS!D$2:D$27," ",0,1) -> 31693.11 | E10: =_xlfn.XLOOKUP($A10,IS!$A$2:$A$27,IS!E$2:E$27," ",0,1) -> 28493.12 | F10: =_xlfn.XLOOKUP($A10,IS!$A$2:$A$27,IS!F$2:F$27," ",0,1) -> 26171.85
A11: (b) Purchases of products for sale | B11: =_xlfn.XLOOKUP($A11,IS!$A$2:$A$27,IS!B$2:B$27," ",0,1) -> 6707.03 | C11: =_xlfn.XLOOKUP($A11,IS!$A$2:$A$27,IS!C$2:C$27," ",0,1) -> 6561.32 | D11: =_xlfn.XLOOKUP($A11,IS!$A$2:$A$27,IS!D$2:D$27," ",0,1) -> 5030 | E11: =_xlfn.XLOOKUP($A11,IS!$A$2:$A$27,IS!E$2:E$27," ",0,1) -> 7518.05 | F11: =_xlfn.XLOOKUP($A11,IS!$A$2:$A$27,IS!F$2:F$27," ",0,1) -> 5679.98
A12: (c) Changes in Stock | B12: =_xlfn.XLOOKUP($A12,IS!$A$2:$A$27,IS!B$2:B$27," ",0,1) -> 1736.35 | C12: =_xlfn.XLOOKUP($A12,IS!$A$2:$A$27,IS!C$2:C$27," ",0,1) -> 484.69 | D12: =_xlfn.XLOOKUP($A12,IS!$A$2:$A$27,IS!D$2:D$27," ",0,1) -> -403.87 | E12: =_xlfn.XLOOKUP($A12,IS!$A$2:$A$27,IS!E$2:E$27," ",0,1) -> -108.48 | F12: =_xlfn.XLOOKUP($A12,IS!$A$2:$A$27,IS!F$2:F$27," ",0,1) -> 722.68
A13: (d) Employee benefits expense | B13: =_xlfn.XLOOKUP($A13,IS!$A$2:$A$27,IS!B$2:B$27," ",0,1) -> 4308.15 | C13: =_xlfn.XLOOKUP($A13,IS!$A$2:$A$27,IS!C$2:C$27," ",0,1) -> 4021.63 | D13: =_xlfn.XLOOKUP($A13,IS!$A$2:$A$27,IS!D$2:D$27," ",0,1) -> 3601.51 | E13: =_xlfn.XLOOKUP($A13,IS!$A$2:$A$27,IS!E$2:E$27," ",0,1) -> 3987.72 | F13: =_xlfn.XLOOKUP($A13,IS!$A$2:$A$27,IS!F$2:F$27," ",0,1) -> 4384.31
A14: (e) Finance costs | B14: =_xlfn.XLOOKUP($A14,IS!$A$2:$A$27,IS!B$2:B$27," ",0,1) -> 1705.74 | C14: =_xlfn.XLOOKUP($A14,IS!$A$2:$A$27,IS!C$2:C$27," ",0,1) -> 2047.51 | D14: =_xlfn.XLOOKUP($A14,IS!$A$2:$A$27,IS!D$2:D$27," ",0,1) -> 2121.73 | E14: =_xlfn.XLOOKUP($A14,IS!$A$2:$A$27,IS!E$2:E$27," ",0,1) -> 2288.61 | F14: =_xlfn.XLOOKUP($A14,IS!$A$2:$A$27,IS!F$2:F$27," ",0,1) -> 1973
A15: (f) Foreign exchange loss (net) | B15: =_xlfn.XLOOKUP($A15,IS!$A$2:$A$27,IS!B$2:B$27," ",0,1) -> 200.72 | C15: =_xlfn.XLOOKUP($A15,IS!$A$2:$A$27,IS!C$2:C$27," ",0,1) -> 279.76 | D15: =_xlfn.XLOOKUP($A15,IS!$A$2:$A$27,IS!D$2:D$27," ",0,1) -> 136.81 | E15: =_xlfn.XLOOKUP($A15,IS!$A$2:$A$27,IS!E$2:E$27," ",0,1) -> 29.02 | F15: =_xlfn.XLOOKUP($A15,IS!$A$2:$A$27,IS!F$2:F$27," ",0,1) -> 239
A16: (g) Depreciation and amortisation expense | B16: =_xlfn.XLOOKUP($A16,IS!$A$2:$A$27,IS!B$2:B$27," ",0,1) -> 2016.84 | C16: =_xlfn.XLOOKUP($A16,IS!$A$2:$A$27,IS!C$2:C$27," ",0,1) -> 1766.86 | D16: =_xlfn.XLOOKUP($A16,IS!$A$2:$A$27,IS!D$2:D$27," ",0,1) -> 1760.57 | E16: =_xlfn.XLOOKUP($A16,IS!$A$2:$A$27,IS!E$2:E$27," ",0,1) -> 3325.8 | F16: =_xlfn.XLOOKUP($A16,IS!$A$2:$A$27,IS!F$2:F$27," ",0,1) -> 3375.29
A17: (h) Product development/Engineering expenses | B17: =_xlfn.XLOOKUP($A17,IS!$A$2:$A$27,IS!B$2:B$27," ",0,1) -> 1104.79 | C17: =_xlfn.XLOOKUP($A17,IS!$A$2:$A$27,IS!C$2:C$27," ",0,1) -> 899.06 | D17: =_xlfn.XLOOKUP($A17,IS!$A$2:$A$27,IS!D$2:D$27," ",0,1) -> 593.9 | E17: =_xlfn.XLOOKUP($A17,IS!$A$2:$A$27,IS!E$2:E$27," ",0,1) -> 907.44 | F17: =_xlfn.XLOOKUP($A17,IS!$A$2:$A$27,IS!F$2:F$27," ",0,1) -> 830.24
A18: (i) Other expenses | B18: =_xlfn.XLOOKUP($A18,IS!$A$2:$A$27,IS!B$2:B$27," ",0,1) -> 7610.15 | C18: =_xlfn.XLOOKUP($A18,IS!$A$2:$A$27,IS!C$2:C$27," ",0,1) -> 7819.74 | D18: =_xlfn.XLOOKUP($A18,IS!$A$2:$A$27,IS!D$2:D$27," ",0,1) -> 6018.71 | E18: =_xlfn.XLOOKUP($A18,IS!$A$2:$A$27,IS!E$2:E$27," ",0,1) -> 5612.48 | F18: =_xlfn.XLOOKUP($A18,IS!$A$2:$A$27,IS!F$2:F$27," ",0,1) -> 7720.75
A19: (j) Amount transferred to capital and other accounts | B19: =_xlfn.XLOOKUP($A19,IS!$A$2:$A$27,IS!B$2:B$27," ",0,1) -> -1129.73 | C19: =_xlfn.XLOOKUP($A19,IS!$A$2:$A$27,IS!C$2:C$27," ",0,1) -> -1066.73 | D19: =_xlfn.XLOOKUP($A19,IS!$A$2:$A$27,IS!D$2:D$27," ",0,1) -> -905.42 | E19: =_xlfn.XLOOKUP($A19,IS!$A$2:$A$27,IS!E$2:E$27," ",0,1) -> -817.53 | F19: =_xlfn.XLOOKUP($A19,IS!$A$2:$A$27,IS!F$2:F$27," ",0,1) -> -1169.46
A20: Total Expenses (IV) | B20: =_xlfn.XLOOKUP($A20,IS!$A$2:$A$27,IS!B$2:B$27," ",0,1) -> 69317.32 | C20: =_xlfn.XLOOKUP($A20,IS!$A$2:$A$27,IS!C$2:C$27," ",0,1) -> 65040.65 | D20: =_xlfn.XLOOKUP($A20,IS!$A$2:$A$27,IS!D$2:D$27," ",0,1) -> 49647.05 | E20: =_xlfn.XLOOKUP($A20,IS!$A$2:$A$27,IS!E$2:E$27," ",0,1) -> 51239.38 | F20: =_xlfn.XLOOKUP($A20,IS!$A$2:$A$27,IS!F$2:F$27," ",0,1) -> 49927.64
A21: V. Profit/(Loss) before exceptional items and tax (III-IV) | B21: =_xlfn.XLOOKUP($A21,IS!$A$2:$A$27,IS!B$2:B$27," ",0,1) -> 5135.64 | C21: =_xlfn.XLOOKUP($A21,IS!$A$2:$A$27,IS!C$2:C$27," ",0,1) -> 1537.62 | D21: =_xlfn.XLOOKUP($A21,IS!$A$2:$A$27,IS!D$2:D$27," ",0,1) -> -1723.46 | E21: =_xlfn.XLOOKUP($A21,IS!$A$2:$A$27,IS!E$2:E$27," ",0,1) -> -3364.95 | F21: =_xlfn.XLOOKUP($A21,IS!$A$2:$A$27,IS!F$2:F$27," ",0,1) -> -4616.42
... A27: XI. Total comprehensive income/(loss) for the year | B27: =_xlfn.XLOOKUP($A27,IS!$A$2:$A$27,IS!B$2:B$27," ",0,1) -> 8338.64 | C27: =_xlfn.XLOOKUP($A27,IS!$A$2:$A$27,IS!C$2:C$27," ",0,1) -> 2451.64 | D27: =_xlfn.XLOOKUP($A27,IS!$A$2:$A$27,IS!D$2:D$27," ",0,1) -> -1267.18 | E27: =_xlfn.XLOOKUP($A27,IS!$A$2:$A$27,IS!E$2:E$27," ",0,1) -> -1952.45 | F27: =_xlfn.XLOOKUP($A27,IS!$A$2:$A$27,IS!F$2:F$27," ",0,1) -> -7668.35

Sheet ISCOMP
A1: Comparative Income Statement of Tata Motors from FY2020 TO FY2024
A2: Particulars | B2: FY2024 | C2: FY2023 | D2: FY2022 | E2: FY2021 | F2: FY2020
A3: I. Revenue from operations
A4: (a) Revenue | B4: =IFERROR((_xlfn.XLOOKUP($A4,IS!$A$2:$A$27,IS!B$2:B$27," ",0,1)/_xlfn.XLOOKUP($A4,IS!$A$2:$A$27,IS!C$2:C$27," ",0,1))-1,"") -> 0.11404613 | C4: =IFERROR((_xlfn.XLOOKUP($A4,IS!$A$2:$A$27,IS!C$2:C$27," ",0,1)/_xlfn.XLOOKUP($A4,IS!$A$2:$A$27,IS!D$2:D$27," ",0,1))-1,"") -> 0.39286452 | D4: =IFERROR((_xlfn.XLOOKUP($A4,IS!$A$2:$A$27,IS!D$2:D$27," ",0,1)/_xlfn.XLOOKUP($A4,IS!$A$2:$A$27,IS!E$2:E$27," ",0,1))-1,"") -> 0.0069068774 | E4: =IFERROR((_xlfn.XLOOKUP($A4,IS!$A$2:$A$27,IS!E$2:E$27," ",0,1)/_xlfn.XLOOKUP($A4,IS!$A$2:$A$27,IS!F$2:F$27," ",0,1))-1,"") -> 0.070681299
A5: (b) Other operating revenue | B5: =IFERROR((_xlfn.XLOOKUP($A5,IS!$A$2:$A$27,IS!B$2:B$27," ",0,1)/_xlfn.XLOOKUP($A5,IS!$A$2:$A$27,IS!C$2:C$27," ",0,1))-1,"") -> 0.21520644 | C5: =IFERROR((_xlfn.XLOOKUP($A5,IS!$A$2:$A$27,IS!C$2:C$27," ",0,1)/_xlfn.XLOOKUP($A5,IS!$A$2:$A$27,IS!D$2:D$27," ",0,1))-1,"") -> 0.19800894 | D5: =IFERROR((_xlfn.XLOOKUP($A5,IS!$A$2:$A$27,IS!D$2:D$27," ",0,1)/_xlfn.XLOOKUP($A5,IS!$A$2:$A$27,IS!E$2:E$27," ",0,1))-1,"") -> -0.18931113 | E5: =IFERROR((_xlfn.XLOOKUP($A5,IS!$A$2:$A$27,IS!E$2:E$27," ",0,1)/_xlfn.XLOOKUP($A5,IS!$A$2:$A$27,IS!F$2:F$27," ",0,1))-1,"") -> 0.067064488
A6: Total revenue from operations (I) | B6: =IFERROR((_xlfn.XLOOKUP($A6,IS!$A$2:$A$27,IS!B$2:B$27," ",0,1)/_xlfn.XLOOKUP($A6,IS!$A$2:$A$27,IS!C$2:C$27," ",0,1))-1,"") -> 0.11475147 | C6: =IFERROR((_xlfn.XLOOKUP($A6,IS!$A$2:$A$27,IS!C$2:C$27," ",0,1)/_xlfn.XLOOKUP($A6,IS!$A$2:$A$27,IS!D$2:D$27," ",0,1))-1,"") -> 0.39128671 | D6: =IFERROR((_xlfn.XLOOKUP($A6,IS!$A$2:$A$27,IS!D$2:D$27," ",0,1)/_xlfn.XLOOKUP($A6,IS!$A$2:$A$27,IS!E$2:E$27," ",0,1))-1,"") -> 0.0049373324 | E6: =IFERROR((_xlfn.XLOOKUP($A6,IS!$A$2:$A$27,IS!E$2:E$27," ",0,1)/_xlfn.XLOOKUP($A6,IS!$A$2:$A$27,IS!F$2:F$27," ",0,1))-1,"") -> 0.070644873
A7: II. Other Income | B7: =IFERROR((_xlfn.XLOOKUP($A7,IS!$A$2:$A$27,IS!B$2:B$27," ",0,1)/_xlfn.XLOOKUP($A7,IS!$A$2:$A$27,IS!C$2:C$27," ",0,1))-1,"") -> 0.40068702 | C7: =IFERROR((_xlfn.XLOOKUP($A7,IS!$A$2:$A$27,IS!C$2:C$27," ",0,1)/_xlfn.XLOOKUP($A7,IS!$A$2:$A$27,IS!D$2:D$27," ",0,1))-1,"") -> 0.24401812 | D7: =IFERROR((_xlfn.XLOOKUP($A7,IS!$A$2:$A$27,IS!D$2:D$27," ",0,1)/_xlfn.XLOOKUP($A7,IS!$A$2:$A$27,IS!E$2:E$27," ",0,1))-1,"") -> -0.21715147 | E7: =IFERROR((_xlfn.XLOOKUP($A7,IS!$A$2:$A$27,IS!E$2:E$27," ",0,1)/_xlfn.XLOOKUP($A7,IS!$A$2:$A$27,IS!F$2:F$27," ",0,1))-1,"") -> -0.39050649
A8: III. Total Income (I+II) | B8: =IFERROR((_xlfn.XLOOKUP($A8,IS!$A$2:$A$27,IS!B$2:B$27," ",0,1)/_xlfn.XLOOKUP($A8,IS!$A$2:$A$27,IS!C$2:C$27," ",0,1))-1,"") -> 0.11827718 | C8: =IFERROR((_xlfn.XLOOKUP($A8,IS!$A$2:$A$27,IS!C$2:C$27," ",0,1)/_xlfn.XLOOKUP($A8,IS!$A$2:$A$27,IS!D$2:D$27," ",0,1))-1,"") -> 0.38925882 | D8: =IFERROR((_xlfn.XLOOKUP($A8,IS!$A$2:$A$27,IS!D$2:D$27," ",0,1)/_xlfn.XLOOKUP($A8,IS!$A$2:$A$27,IS!E$2:E$27," ",0,1))-1,"") -> 0.001026853 | E8: =IFERROR((_xlfn.XLOOKUP($A8,IS!$A$2:$A$27,IS!E$2:E$27," ",0,1)/_xlfn.XLOOKUP($A8,IS!$A$2:$A$27,IS!F$2:F$27," ",0,1))-1,"") -> 0.056568991
A9: IV. Expenses: | B9: =IFERROR((_xlfn.XLOOKUP($A9,IS!$A$2:$A$27,IS!B$2:B$27," ",0,1)/_xlfn.XLOOKUP($A9,IS!$A$2:$A$27,IS!C$2:C$27," ",0,1))-1,"") | C9: =IFERROR((_xlfn.XLOOKUP($A9,IS!$A$2:$A$27,IS!C$2:C$27," ",0,1)/_xlfn.XLOOKUP($A9,IS!$A$2:$A$27,IS!D$2:D$27," ",0,1))-1,"") | D9: =IFERROR((_xlfn.XLOOKUP($A9,IS!$A$2:$A$27,IS!D$2:D$27," ",0,1)/_xlfn.XLOOKUP($A9,IS!$A$2:$A$27,IS!E$2:E$27," ",0,1))-1,"") | E9: =IFERROR((_xlfn.XLOOKUP($A9,IS!$A$2:$A$27,IS!E$2:E$27," ",0,1)/_xlfn.XLOOKUP($A9,IS!$A$2:$A$27,IS!F$2:F$27," ",0,1))-1,"")
A10: (a) Cost of materials consumed | B10: =IFERROR((_xlfn.XLOOKUP($A10,IS!$A$2:$A$27,IS!B$2:B$27," ",0,1)/_xlfn.XLOOKUP($A10,IS!$A$2:$A$27,IS!C$2:C$27," ",0,1))-1,"") -> 0.10728895 | C10: =IFERROR((_xlfn.XLOOKUP($A10,IS!$A$2:$A$27,IS!C$2:C$27," ",0,1)/_xlfn.XLOOKUP($A10,IS!$A$2:$A$27,IS!D$2:D$27," ",0,1))-1,"") -> 0.33236562 | D10: =IFERROR((_xlfn.XLOOKUP($A10,IS!$A$2:$A$27,IS!D$2:D$27," ",0,1)/_xlfn.XLOOKUP($A10,IS!$A$2:$A$27,IS!E$2:E$27," ",0,1))-1,"") -> 0.11230746 | E10: =IFERROR((_xlfn.XLOOKUP($A10,IS!$A$2:$A$27,IS!E$2:E$27," ",0,1)/_xlfn.XLOOKUP($A10,IS!$A$2:$A$27,IS!F$2:F$27," ",0,1))-1,"") -> 0.088693386
A11: (b) Purchases of products for sale | B11: =IFERROR((_xlfn.XLOOKUP($A11,IS!$A$2:$A$27,IS!B$2:B$27," ",0,1)/_xlfn.XLOOKUP($A11,IS!$A$2:$A$27,IS!C$2:C$27," ",0,1))-1,"") -> 0.022207422 | C11: =IFERROR((_xlfn.XLOOKUP($A11,IS!$A$2:$A$27,IS!C$2:C$27," ",0,1)/_xlfn.XLOOKUP($A11,IS!$A$2:$A$27,IS!D$2:D$27," ",0,1))-1,"") -> 0.30443738 | D11: =IFERROR((_xlfn.XLOOKUP($A11,IS!$A$2:$A$27,IS!D$2:D$27," ",0,1)/_xlfn.XLOOKUP($A11,IS!$A$2:$A$27,IS!E$2:E$27," ",0,1))-1,"") -> -0.33094353 | E11: =IFERROR((_xlfn.XLOOKUP($A11,IS!$A$2:$A$27,IS!E$2:E$27," ",0,1)/_xlfn.XLOOKUP($A11,IS!$A$2:$A$27,IS!F$2:F$27," ",0,1))-1,"") -> 0.32360501
A12: (c) Changes in Stock | B12: =IFERROR((_xlfn.XLOOKUP($A12,IS!$A$2:$A$27,IS!B$2:B$27," ",0,1)/_xlfn.XLOOKUP($A12,IS!$A$2:$A$27,IS!C$2:C$27," ",0,1))-1,"") -> 2.5823929 | C12: =IFERROR((_xlfn.XLOOKUP($A12,IS!$A$2:$A$27,IS!C$2:C$27," ",0,1)/_xlfn.XLOOKUP($A12,IS!$A$2:$A$27,IS!D$2:D$27," ",0,1))-1,"") -> -2.2001139 | D12: =IFERROR((_xlfn.XLOOKUP($A12,IS!$A$2:$A$27,IS!D$2:D$27," ",0,1)/_xlfn.XLOOKUP($A12,IS!$A$2:$A$27,IS!E$2:E$27," ",0,1))-1,"") -> 2.7229904 | E12: =IFERROR((_xlfn.XLOOKUP($A12,IS!$A$2:$A$27,IS!E$2:E$27," ",0,1)/_xlfn.XLOOKUP($A12,IS!$A$2:$A$27,IS!F$2:F$27," ",0,1))-1,"") -> -1.1501079
A13: (d) Employee benefits expense | B13: =IFERROR((_xlfn.XLOOKUP($A13,IS!$A$2:$A$27,IS!B$2:B$27," ",0,1)/_xlfn.XLOOKUP($A13,IS!$A$2:$A$27,IS!C$2:C$27," ",0,1))-1,"") -> 0.071244744 | C13: =IFERROR((_xlfn.XLOOKUP($A13,IS!$A$2:$A$27,IS!C$2:C$27," ",0,1)/_xlfn.XLOOKUP($A13,IS!$A$2:$A$27,IS!D$2:D$27," ",0,1))-1,"") -> 0.11665107 | D13: =IFERROR((_xlfn.XLOOKUP($A13,IS!$A$2:$A$27,IS!D$2:D$27," ",0,1)/_xlfn.XLOOKUP($A13,IS!$A$2:$A$27,IS!E$2:E$27," ",0,1))-1,"") -> -0.096849829 | E13: =IFERROR((_xlfn.XLOOKUP($A13,IS!$A$2:$A$27,IS!E$2:E$27," ",0,1)/_xlfn.XLOOKUP($A13,IS!$A$2:$A$27,IS!F$2:F$27," ",0,1))-1,"") -> -0.090456651
A14: (e) Finance costs | B14: =IFERROR((_xlfn.XLOOKUP($A14,IS!$A$2:$A$27,IS!B$2:B$27," ",0,1)/_xlfn.XLOOKUP($A14,IS!$A$2:$A$27,IS!C$2:C$27," ",0,1))-1,"") -> -0.16691982 | C14: =IFERROR((_xlfn.XLOOKUP($A14,IS!$A$2:$A$27,IS!C$2:C$27," ",0,1)/_xlfn.XLOOKUP($A14,IS!$A$2:$A$27,IS!D$2:D$27," ",0,1))-1,"") -> -0.034980888 | D14: =IFERROR((_xlfn.XLOOKUP($A14,IS!$A$2:$A$27,IS!D$2:D$27," ",0,1)/_xlfn.XLOOKUP($A14,IS!$A$2:$A$27,IS!E$2:E$27," ",0,1))-1,"") -> -0.072917622 | E14: =IFERROR((_xlfn.XLOOKUP($A14,IS!$A$2:$A$27,IS!E$2:E$27," ",0,1)/_xlfn.XLOOKUP($A14,IS!$A$2:$A$27,IS!F$2:F$27," ",0,1))-1,"") -> 0.15996452
A15: (f) Foreign exchange loss (net) | B15: =IFERROR((_xlfn.XLOOKUP($A15,IS!$A$2:$A$27,IS!B$2:B$27," ",0,1)/_xlfn.XLOOKUP($A15,IS!$A$2:$A$27,IS!C$2:C$27," ",0,1))-1,"") -> -0.28252788 | C15: =IFERROR((_xlfn.XLOOKUP($A15,IS!$A$2:$A$27,IS!C$2:C$27," ",0,1)/_xlfn.XLOOKUP($A15,IS!$A$2:$A$27,IS!D$2:D$27," ",0,1))-1,"") -> 1.0448798 | D15: =IFERROR((_xlfn.XLOOKUP($A15,IS!$A$2:$A$27,IS!D$2:D$27," ",0,1)/_xlfn.XLOOKUP($A15,IS!$A$2:$A$27,IS!E$2:E$27," ",0,1))-1,"") -> 3.7143349 | E15: =IFERROR((_xlfn.XLOOKUP($A15,IS!$A$2:$A$27,IS!E$2:E$27," ",0,1)/_xlfn.XLOOKUP($A15,IS!$A$2:$A$27,IS!F$2:F$27," ",0,1))-1,"") -> -0.87857741
... A27: XI. Total comprehensive income/(loss) for the year | B27: =IFERROR((_xlfn.XLOOKUP($A27,IS!$A$2:$A$27,IS!B$2:B$27," ",0,1)/_xlfn.XLOOKUP($A27,IS!$A$2:$A$27,IS!C$2:C$27," ",0,1))-1,"") -> 2.4012498 | C27: =IFERROR((_xlfn.XLOOKUP($A27,IS!$A$2:$A$27,IS!C$2:C$27," ",0,1)/_xlfn.XLOOKUP($A27,IS!$A$2:$A$27,IS!D$2:D$27," ",0,1))-1,"") -> -2.9347212 | D27: =IFERROR((_xlfn.XLOOKUP($A27,IS!$A$2:$A$27,IS!D$2:D$27," ",0,1)/_xlfn.XLOOKUP($A27,IS!$A$2:$A$27,IS!E$2:E$27," ",0,1))-1,"") -> -0.35097954 | E27: =IFERROR((_xlfn.XLOOKUP($A27,IS!$A$2:$A$27,IS!E$2:E$27," ",0,1)/_xlfn.XLOOKUP($A27,IS!$A$2:$A$27,IS!F$2:F$27," ",0,1))-1,"") -> -0.74538851

Sheet BS_XLOOKUP
A1: Comparative Balance Sheet of Tata Motors from FY2020 TO FY2024
A2: Particulars | B2: FY2024 | C2: FY2023 | D2: FY2022 | E2: FY2021 | F2: FY2020
A3: I. ASSETS
A4: (1) NON-CURRENT ASSETS
A5: Property, plant and equipment (PPE) | B5: =_xlfn.XLOOKUP($A5,BS!$A$2:$A$36,BS!B$2:B$36," ",0,1) -> 12056.24 | C5: =_xlfn.XLOOKUP($A5,BS!$A$2:$A$36,BS!C$2:C$36," ",0,1) -> 12176.6 | D5: =_xlfn.XLOOKUP($A5,BS!$A$2:$A$36,BS!D$2:D$36," ",0,1) -> 11811.02 | E5: =_xlfn.XLOOKUP($A5,BS!$A$2:$A$36,BS!E$2:E$36," ",0,1) -> 17143.04 | F5: =_xlfn.XLOOKUP($A5,BS!$A$2:$A$36,BS!F$2:F$36," ",0,1) -> 18870.67
A6: Capital work-in-progress (CWIP) | B6: =_xlfn.XLOOKUP($A6,BS!$A$2:$A$36,BS!B$2:B$36," ",0,1) -> 575.65 | C6: =_xlfn.XLOOKUP($A6,BS!$A$2:$A$36,BS!C$2:C$36," ",0,1) -> 575.65 | D6: =_xlfn.XLOOKUP($A6,BS!$A$2:$A$36,BS!D$2:D$36," ",0,1) -> 585.21 | E6: =_xlfn.XLOOKUP($A6,BS!$A$2:$A$36,BS!E$2:E$36," ",0,1) -> 1324.21 | F6: =_xlfn.XLOOKUP($A6,BS!$A$2:$A$36,BS!F$2:F$36," ",0,1) -> 1755.51
A7: Right of use assets (ROU) | B7: =_xlfn.XLOOKUP($A7,BS!$A$2:$A$36,BS!B$2:B$36," ",0,1) -> 338.25 | C7: =_xlfn.XLOOKUP($A7,BS!$A$2:$A$36,BS!C$2:C$36," ",0,1) -> 344.2 | D7: =_xlfn.XLOOKUP($A7,BS!$A$2:$A$36,BS!D$2:D$36," ",0,1) -> 332.45 | E7: =_xlfn.XLOOKUP($A7,BS!$A$2:$A$36,BS!E$2:E$36," ",0,1) -> 979.48 | F7: =_xlfn.XLOOKUP($A7,BS!$A$2:$A$36,BS!F$2:F$36," ",0,1) -> 669.58
A8: Goodwill | B8: =_xlfn.XLOOKUP($A8,BS!$A$2:$A$36,BS!B$2:B$36," ",0,1) -> 99.09 | C8: =_xlfn.XLOOKUP($A8,BS!$A$2:$A$36,BS!C$2:C$36," ",0,1) -> 99.09 | D8: =_xlfn.XLOOKUP($A8,BS!$A$2:$A$36,BS!D$2:D$36," ",0,1) -> 99.09 | E8: =_xlfn.XLOOKUP($A8,BS!$A$2:$A$36,BS!E$2:E$36," ",0,1) -> 99.09 | F8: =_xlfn.XLOOKUP($A8,BS!$A$2:$A$36,BS!F$2:F$36," ",0,1) -> 99.09
A9: Other intangible assets | B9: =_xlfn.XLOOKUP($A9,BS!$A$2:$A$36,BS!B$2:B$36," ",0,1) -> 1768.49 | C9: =_xlfn.XLOOKUP($A9,BS!$A$2:$A$36,BS!C$2:C$36," ",0,1) -> 1914.76 | D9: =_xlfn.XLOOKUP($A9,BS!$A$2:$A$36,BS!D$2:D$36," ",0,1) -> 2009.87 | E9: =_xlfn.XLOOKUP($A9,BS!$A$2:$A$36,BS!E$2:E$36," ",0,1) -> 6156.56 | F9: =_xlfn.XLOOKUP($A9,BS!$A$2:$A$36,BS!F$2:F$36," ",0,1) -> 5568.64
A10: Intangible assets under development | B10: =_xlfn.XLOOKUP($A10,BS!$A$2:$A$36,BS!B$2:B$36," ",0,1) -> 509.3 | C10: =_xlfn.XLOOKUP($A10,BS!$A$2:$A$36,BS!C$2:C$36," ",0,1) -> 509.3 | D10: =_xlfn.XLOOKUP($A10,BS!$A$2:$A$36,BS!D$2:D$36," ",0,1) -> 882.03 | E10: =_xlfn.XLOOKUP($A10,BS!$A$2:$A$36,BS!E$2:E$36," ",0,1) -> 1604.23 | F10: =_xlfn.XLOOKUP($A10,BS!$A$2:$A$36,BS!F$2:F$36," ",0,1) -> 2739.29
A11: Investments in subsidiaries, JVs & associates | B11: =_xlfn.XLOOKUP($A11,BS!$A$2:$A$36,BS!B$2:B$36," ",0,1) -> 25819.34 | C11: =_xlfn.XLOOKUP($A11,BS!$A$2:$A$36,BS!C$2:C$36," ",0,1) -> 27976.8 | D11: =_xlfn.XLOOKUP($A11,BS!$A$2:$A$36,BS!D$2:D$36," ",0,1) -> 24723.34 | E11: =_xlfn.XLOOKUP($A11,BS!$A$2:$A$36,BS!E$2:E$36," ",0,1) -> 14287.8 | F11: =_xlfn.XLOOKUP($A11,BS!$A$2:$A$36,BS!F$2:F$36," ",0,1) -> 15182.29
A12: Financial assets (Investments, Loans, Others) | B12: =_xlfn.XLOOKUP($A12,BS!$A$2:$A$36,BS!B$2:B$36," ",0,1) -> -1283.47 | C12: =_xlfn.XLOOKUP($A12,BS!$A$2:$A$36,BS!C$2:C$36," ",0,1) -> -1402.16 | D12: =_xlfn.XLOOKUP($A12,BS!$A$2:$A$36,BS!D$2:D$36," ",0,1) -> -1507.57 | E12: =_xlfn.XLOOKUP($A12,BS!$A$2:$A$36,BS!E$2:E$36," ",0,1) -> 1691.01 | F12: =_xlfn.XLOOKUP($A12,BS!$A$2:$A$36,BS!F$2:F$36," ",0,1) -> 2204.53
A13: Non-current tax assets (Net) | B13: =_xlfn.XLOOKUP($A13,BS!$A$2:$A$36,BS!B$2:B$36," ",0,1) -> 1751.48 | C13: =_xlfn.XLOOKUP($A13,BS!$A$2:$A$36,BS!C$2:C$36," ",0,1) -> 1909.8 | D13: =_xlfn.XLOOKUP($A13,BS!$A$2:$A$36,BS!D$2:D$36," ",0,1) -> 1847.16 | E13: =_xlfn.XLOOKUP($A13,BS!$A$2:$A$36,BS!E$2:E$36," ",0,1) -> 741.02 | F13: =_xlfn.XLOOKUP($A13,BS!$A$2:$A$36,BS!F$2:F$36," ",0,1) -> 727.97
A14: Other non-current assets | B14: =_xlfn.XLOOKUP($A14,BS!$A$2:$A$36,BS!B$2:B$36," ",0,1) -> -1301.98 | C14: =_xlfn.XLOOKUP($A14,BS!$A$2:$A$36,BS!C$2:C$36," ",0,1) -> -1439.42 | D14: =_xlfn.XLOOKUP($A14,BS!$A$2:$A$36,BS!D$2:D$36," ",0,1) -> -2059.45 | E14: =_xlfn.XLOOKUP($A14,BS!$A$2:$A$36,BS!E$2:E$36," ",0,1) -> 1056.77 | F14: =_xlfn.XLOOKUP($A14,BS!$A$2:$A$36,BS!F$2:F$36," ",0,1) -> 1208.08
A15: (2) CURRENT ASSETS | B15: =_xlfn.XLOOKUP($A15,BS!$A$2:$A$36,BS!B$2:B$36," ",0,1) -> 36258.71 | C15: =_xlfn.XLOOKUP($A15,BS!$A$2:$A$36,BS!C$2:C$36," ",0,1) -> 26868.97 | D15: =_xlfn.XLOOKUP($A15,BS!$A$2:$A$36,BS!D$2:D$36," ",0,1) -> 26792.13 | E15: =_xlfn.XLOOKUP($A15,BS!$A$2:$A$36,BS!E$2:E$36," ",0,1) -> 25309.78 | F15: =_xlfn.XLOOKUP($A15,BS!$A$2:$A$36,BS!F$2:F$36," ",0,1) -> 7861.82
A16: Inventories | B16: =_xlfn.XLOOKUP($A16,BS!$A$2:$A$36,BS!B$2:B$36," ",0,1) -> 8247.78 | C16: =_xlfn.XLOOKUP($A16,BS!$A$2:$A$36,BS!C$2:C$36," ",0,1) -> 5515.22 | D16: =_xlfn.XLOOKUP($A16,BS!$A$2:$A$36,BS!D$2:D$36," ",0,1) -> 5348.88 | E16: =_xlfn.XLOOKUP($A16,BS!$A$2:$A$36,BS!E$2:E$36," ",0,1) -> 5084.7 | F16: =_xlfn.XLOOKUP($A16,BS!$A$2:$A$36,BS!F$2:F$36," ",0,1) -> 6654.89
... A20: TOTAL ASSETS (1) + (2) | B20: =_xlfn.XLOOKUP($A20,BS!$A$2:$A$36,BS!B$2:B$36," ",0,1) -> 72391.8 | C20: =_xlfn.XLOOKUP($A20,BS!$A$2:$A$36,BS!C$2:C$36," ",0,1) -> 59929.19 | D20: =_xlfn.XLOOKUP($A20,BS!$A$2:$A$36,BS!D$2:D$36," ",0,1) -> 57750.95 | E20: =_xlfn.XLOOKUP($A20,BS!$A$2:$A$36,BS!E$2:E$36," ",0,1) -> 55593.43 | F20: =_xlfn.XLOOKUP($A20,BS!$A$2:$A$36,BS!F$2:F$36," ",0,1) -> 55103.88
A22: II. EQUITY AND LIABILITIES
A23: (1) EQUITY
A24: Equity share capital
A25: Other equity
A26: (2) NON-CURRENT LIABILITIES
A27: Financial liabilities (Borrowings & Lease)
A28: Provisions
A29: Deferred tax liabilities (Net)
A30: Other non-current liabilities
A31: (3) CURRENT LIABILITIES
A32: Financial liabilities (Borrowings, Trade Payables, Others)
A33: Provisions
... A36: TOTAL EQUITY AND LIABILITIES (1) + (2) + (3)

Sheet BSCOMP
A1: Comparative Balance Sheet of Tata Motors from FY2020 TO FY2024
A2: Particulars | B2: FY2024 | C2: FY2023 | D2: FY2022 | E2: FY2021 | F2: FY2020
A3: I. ASSETS
A4: (1) NON-CURRENT ASSETS
A5: Property, plant and equipment (PPE) | B5: =IFERROR(_xlfn.XLOOKUP($A5,BS!$A$2:$A$36,BS!B$2:B$36," ",0,1)/_xlfn.XLOOKUP($A5,BS!$A$2:$A$36,BS!C$2:C$36,"",0,1)-1, "") -> -0.0098845326 | C5: =IFERROR(_xlfn.XLOOKUP($A5,BS!$A$2:$A$36,BS!C$2:C$36," ",0,1)/_xlfn.XLOOKUP($A5,BS!$A$2:$A$36,BS!D$2:D$36,"",0,1)-1, "") -> 0.030952449 | D5: =IFERROR(_xlfn.XLOOKUP($A5,BS!$A$2:$A$36,BS!D$2:D$36," ",0,1)/_xlfn.XLOOKUP($A5,BS!$A$2:$A$36,BS!E$2:E$36,"",0,1)-1, "") -> -0.31103118 | E5: =IFERROR(_xlfn.XLOOKUP($A5,BS!$A$2:$A$36,BS!E$2:E$36," ",0,1)/_xlfn.XLOOKUP($A5,BS!$A$2:$A$36,BS!F$2:F$36,"",0,1)-1, "") -> -0.091551068 | F5: =IFERROR(_xlfn.XLOOKUP($A5,BS!$A$2:$A$36,BS!F$2:F$36," ",0,1)/_xlfn.XLOOKUP($A5,BS!$A$2:$A$36,BS!G$2:G$36,"",0,1), "")
A6: Capital work-in-progress (CWIP) | B6: =IFERROR(_xlfn.XLOOKUP($A6,BS!$A$2:$A$36,BS!B$2:B$36," ",0,1)/_xlfn.XLOOKUP($A6,BS!$A$2:$A$36,BS!C$2:C$36,"",0,1)-1, "") -> 0 | C6: =IFERROR(_xlfn.XLOOKUP($A6,BS!$A$2:$A$36,BS!C$2:C$36," ",0,1)/_xlfn.XLOOKUP($A6,BS!$A$2:$A$36,BS!D$2:D$36,"",0,1)-1, "") -> -0.016336016 | D6: =IFERROR(_xlfn.XLOOKUP($A6,BS!$A$2:$A$36,BS!D$2:D$36," ",0,1)/_xlfn.XLOOKUP($A6,BS!$A$2:$A$36,BS!E$2:E$36,"",0,1)-1, "") -> -0.55806858 | E6: =IFERROR(_xlfn.XLOOKUP($A6,BS!$A$2:$A$36,BS!E$2:E$36," ",0,1)/_xlfn.XLOOKUP($A6,BS!$A$2:$A$36,BS!F$2:F$36,"",0,1)-1, "") -> -0.24568359
A7: Right of use assets (ROU) | B7: =IFERROR(_xlfn.XLOOKUP($A7,BS!$A$2:$A$36,BS!B$2:B$36," ",0,1)/_xlfn.XLOOKUP($A7,BS!$A$2:$A$36,BS!C$2:C$36,"",0,1)-1, "") -> -0.017286461 | C7: =IFERROR(_xlfn.XLOOKUP($A7,BS!$A$2:$A$36,BS!C$2:C$36," ",0,1)/_xlfn.XLOOKUP($A7,BS!$A$2:$A$36,BS!D$2:D$36,"",0,1)-1, "") -> 0.035343661 | D7: =IFERROR(_xlfn.XLOOKUP($A7,BS!$A$2:$A$36,BS!D$2:D$36," ",0,1)/_xlfn.XLOOKUP($A7,BS!$A$2:$A$36,BS!E$2:E$36,"",0,1)-1, "") -> -0.66058521 | E7: =IFERROR(_xlfn.XLOOKUP($A7,BS!$A$2:$A$36,BS!E$2:E$36," ",0,1)/_xlfn.XLOOKUP($A7,BS!$A$2:$A$36,BS!F$2:F$36,"",0,1)-1, "") -> 0.46282744
A8: Goodwill | B8: =IFERROR(_xlfn.XLOOKUP($A8,BS!$A$2:$A$36,BS!B$2:B$36," ",0,1)/_xlfn.XLOOKUP($A8,BS!$A$2:$A$36,BS!C$2:C$36,"",0,1)-1, "") -> 0 | C8: =IFERROR(_xlfn.XLOOKUP($A8,BS!$A$2:$A$36,BS!C$2:C$36," ",0,1)/_xlfn.XLOOKUP($A8,BS!$A$2:$A$36,BS!D$2:D$36,"",0,1)-1, "") -> 0 | D8: =IFERROR(_xlfn.XLOOKUP($A8,BS!$A$2:$A$36,BS!D$2:D$36," ",0,1)/_xlfn.XLOOKUP($A8,BS!$A$2:$A$36,BS!E$2:E$36,"",0,1)-1, "") -> 0 | E8: =IFERROR(_xlfn.XLOOKUP($A8,BS!$A$2:$A$36,BS!E$2:E$36," ",0,1)/_xlfn.XLOOKUP($A8,BS!$A$2:$A$36,BS!F$2:F$36,"",0,1)-1, "") -> 0
A9: Other intangible assets | B9: =IFERROR(_xlfn.XLOOKUP($A9,BS!$A$2:$A$36,BS!B$2:B$36," ",0,1)/_xlfn.XLOOKUP($A9,BS!$A$2:$A$36,BS!C$2:C$36,"",0,1)-1, "") -> -0.076390775 | C9: =IFERROR(_xlfn.XLOOKUP($A9,BS!$A$2:$A$36,BS!C$2:C$36," ",0,1)/_xlfn.XLOOKUP($A9,BS!$A$2:$A$36,BS!D$2:D$36,"",0,1)-1, "") -> -0.047321469 | D9: =IFERROR(_xlfn.XLOOKUP($A9,BS!$A$2:$A$36,BS!D$2:D$36," ",0,1)/_xlfn.XLOOKUP($A9,BS!$A$2:$A$36,BS!E$2:E$36,"",0,1)-1, "") -> -0.67354009 | E9: =IFERROR(_xlfn.XLOOKUP($A9,BS!$A$2:$A$36,BS!E$2:E$36," ",0,1)/_xlfn.XLOOKUP($A9,BS!$A$2:$A$36,BS!F$2:F$36,"",0,1)-1, "") -> 0.10557695
A10: Intangible assets under development | B10: =IFERROR(_xlfn.XLOOKUP($A10,BS!$A$2:$A$36,BS!B$2:B$36," ",0,1)/_xlfn.XLOOKUP($A10,BS!$A$2:$A$36,BS!C$2:C$36,"",0,1)-1, "") -> 0 | C10: =IFERROR(_xlfn.XLOOKUP($A10,BS!$A$2:$A$36,BS!C$2:C$36," ",0,1)/_xlfn.XLOOKUP($A10,BS!$A$2:$A$36,BS!D$2:D$36,"",0,1)-1, "") -> -0.422582 | D10: =IFERROR(_xlfn.XLOOKUP($A10,BS!$A$2:$A$36,BS!D$2:D$36," ",0,1)/_xlfn.XLOOKUP($A10,BS!$A$2:$A$36,BS!E$2:E$36,"",0,1)-1, "") -> -0.45018482 | E10: =IFERROR(_xlfn.XLOOKUP($A10,BS!$A$2:$A$36,BS!E$2:E$36," ",0,1)/_xlfn.XLOOKUP($A10,BS!$A$2:$A$36,BS!F$2:F$36,"",0,1)-1, "") -> -0.41436285
A11: Investments in subsidiaries, JVs & associates | B11: =IFERROR(_xlfn.XLOOKUP($A11,BS!$A$2:$A$36,BS!B$2:B$36," ",0,1)/_xlfn.XLOOKUP($A11,BS!$A$2:$A$36,BS!C$2:C$36,"",0,1)-1, "") -> -0.077116039 | C11: =IFERROR(_xlfn.XLOOKUP($A11,BS!$A$2:$A$36,BS!C$2:C$36," ",0,1)/_xlfn.XLOOKUP($A11,BS!$A$2:$A$36,BS!D$2:D$36,"",0,1)-1, "") -> 0.13159468 | D11: =IFERROR(_xlfn.XLOOKUP($A11,BS!$A$2:$A$36,BS!D$2:D$36," ",0,1)/_xlfn.XLOOKUP($A11,BS!$A$2:$A$36,BS!E$2:E$36,"",0,1)-1, "") -> 0.73038116 | E11: =IFERROR(_xlfn.XLOOKUP($A11,BS!$A$2:$A$36,BS!E$2:E$36," ",0,1)/_xlfn.XLOOKUP($A11,BS!$A$2:$A$36,BS!F$2:F$36,"",0,1)-1, "") -> -0.058916672
A12: Financial assets (Investments, Loans, Others) | B12: =IFERROR(_xlfn.XLOOKUP($A12,BS!$A$2:$A$36,BS!B$2:B$36," ",0,1)/_xlfn.XLOOKUP($A12,BS!$A$2:$A$36,BS!C$2:C$36,"",0,1)-1, "") -> -0.084647972 | C12: =IFERROR(_xlfn.XLOOKUP($A12,BS!$A$2:$A$36,BS!C$2:C$36," ",0,1)/_xlfn.XLOOKUP($A12,BS!$A$2:$A$36,BS!D$2:D$36,"",0,1)-1, "") -> -0.069920468 | D12: =IFERROR(_xlfn.XLOOKUP($A12,BS!$A$2:$A$36,BS!D$2:D$36," ",0,1)/_xlfn.XLOOKUP($A12,BS!$A$2:$A$36,BS!E$2:E$36,"",0,1)-1, "") -> -1.8915205 | E12: =IFERROR(_xlfn.XLOOKUP($A12,BS!$A$2:$A$36,BS!E$2:E$36," ",0,1)/_xlfn.XLOOKUP($A12,BS!$A$2:$A$36,BS!F$2:F$36,"",0,1)-1, "") -> -0.23293854
A13: Non-current tax assets (Net) | B13: =IFERROR(_xlfn.XLOOKUP($A13,BS!$A$2:$A$36,BS!B$2:B$36," ",0,1)/_xlfn.XLOOKUP($A13,BS!$A$2:$A$36,BS!C$2:C$36,"",0,1)-1, "") -> -0.082898733 | C13: =IFERROR(_xlfn.XLOOKUP($A13,BS!$A$2:$A$36,BS!C$2:C$36," ",0,1)/_xlfn.XLOOKUP($A13,BS!$A$2:$A$36,BS!D$2:D$36,"",0,1)-1, "") -> 0.033911518 | D13: =IFERROR(_xlfn.XLOOKUP($A13,BS!$A$2:$A$36,BS!D$2:D$36," ",0,1)/_xlfn.XLOOKUP($A13,BS!$A$2:$A$36,BS!E$2:E$36,"",0,1)-1, "") -> 1.4927262 | E13: =IFERROR(_xlfn.XLOOKUP($A13,BS!$A$2:$A$36,BS!E$2:E$36," ",0,1)/_xlfn.XLOOKUP($A13,BS!$A$2:$A$36,BS!F$2:F$36,"",0,1)-1, "") -> 0.017926563
A14: Other non-current assets | B14: =IFERROR(_xlfn.XLOOKUP($A14,BS!$A$2:$A$36,BS!B$2:B$36," ",0,1)/_xlfn.XLOOKUP($A14,BS!$A$2:$A$36,BS!C$2:C$36,"",0,1)-1, "") -> -0.095482903 | C14: =IFERROR(_xlfn.XLOOKUP($A14,BS!$A$2:$A$36,BS!C$2:C$36," ",0,1)/_xlfn.XLOOKUP($A14,BS!$A$2:$A$36,BS!D$2:D$36,"",0,1)-1, "") -> -0.30106582 | D14: =IFERROR(_xlfn.XLOOKUP($A14,BS!$A$2:$A$36,BS!D$2:D$36," ",0,1)/_xlfn.XLOOKUP($A14,BS!$A$2:$A$36,BS!E$2:E$36,"",0,1)-1, "") -> -2.9488157 | E14: =IFERROR(_xlfn.XLOOKUP($A14,BS!$A$2:$A$36,BS!E$2:E$36," ",0,1)/_xlfn.XLOOKUP($A14,BS!$A$2:$A$36,BS!F$2:F$36,"",0,1)-1, "") -> -0.12524833
A15: (2) CURRENT ASSETS | B15: =IFERROR(_xlfn.XLOOKUP($A15,BS!$A$2:$A$36,BS!B$2:B$36," ",0,1)/_xlfn.XLOOKUP($A15,BS!$A$2:$A$36,BS!C$2:C$36,"",0,1)-1, "") -> 0.34946408 | C15: =IFERROR(_xlfn.XLOOKUP($A15,BS!$A$2:$A$36,BS!C$2:C$36," ",0,1)/_xlfn.XLOOKUP($A15,BS!$A$2:$A$36,BS!D$2:D$36,"",0,1)-1, "") -> 0.0028680064 | D15: =IFERROR(_xlfn.XLOOKUP($A15,BS!$A$2:$A$36,BS!D$2:D$36," ",0,1)/_xlfn.XLOOKUP($A15,BS!$A$2:$A$36,BS!E$2:E$36,"",0,1)-1, "") -> 0.058568269 | E15: =IFERROR(_xlfn.XLOOKUP($A15,BS!$A$2:$A$36,BS!E$2:E$36," ",0,1)/_xlfn.XLOOKUP($A15,BS!$A$2:$A$36,BS!F$2:F$36,"",0,1)-1, "") -> 2.2193283
A16: Inventories | B16: =IFERROR(_xlfn.XLOOKUP($A16,BS!$A$2:$A$36,BS!B$2:B$36," ",0,1)/_xlfn.XLOOKUP($A16,BS!$A$2:$A$36,BS!C$2:C$36,"",0,1)-1, "") -> 0.49545802 | C16: =IFERROR(_xlfn.XLOOKUP($A16,BS!$A$2:$A$36,BS!C$2:C$36," ",0,1)/_xlfn.XLOOKUP($A16,BS!$A$2:$A$36,BS!D$2:D$36,"",0,1)-1, "") -> 0.031098099 | D16: =IFERROR(_xlfn.XLOOKUP($A16,BS!$A$2:$A$36,BS!D$2:D$36," ",0,1)/_xlfn.XLOOKUP($A16,BS!$A$2:$A$36,BS!E$2:E$36,"",0,1)-1, "") -> 0.051955868 | E16: =IFERROR(_xlfn.XLOOKUP($A16,BS!$A$2:$A$36,BS!E$2:E$36," ",0,1)/_xlfn.XLOOKUP($A16,BS!$A$2:$A$36,BS!F$2:F$36,"",0,1)-1, "") -> -0.2359453
A17: Financial assets (Investments, Trade receivables, Cash & Bank, Loans, Others) | B17: =IFERROR(_xlfn.XLOOKUP($A17,BS!$A$2:$A$36,BS!B$2:B$36," ",0,1)/_xlfn.XLOOKUP($A17,BS!$A$2:$A$36,BS!C$2:C$36,"",0,1)-1, "") -> 0.31455767 | C17: =IFERROR(_xlfn.XLOOKUP($A17,BS!$A$2:$A$36,BS!C$2:C$36," ",0,1)/_xlfn.XLOOKUP($A17,BS!$A$2:$A$36,BS!D$2:D$36,"",0,1)-1, "") -> -0.013923742 | D17: =IFERROR(_xlfn.XLOOKUP($A17,BS!$A$2:$A$36,BS!D$2:D$36," ",0,1)/_xlfn.XLOOKUP($A17,BS!$A$2:$A$36,BS!E$2:E$36,"",0,1)-1, "") -> 0.071602672 | E17: =IFERROR(_xlfn.XLOOKUP($A17,BS!$A$2:$A$36,BS!E$2:E$36," ",0,1)/_xlfn.XLOOKUP($A17,BS!$A$2:$A$36,BS!F$2:F$36,"",0,1)-1, "") -> 20.131446
... A20: TOTAL ASSETS (1) + (2) | B20: =IFERROR(_xlfn.XLOOKUP($A20,BS!$A$2:$A$36,BS!B$2:B$36," ",0,1)/_xlfn.XLOOKUP($A20,BS!$A$2:$A$36,BS!C$2:C$36,"",0,1)-1, "") -> 0.20795559 | C20: =IFERROR(_xlfn.XLOOKUP($A20,BS!$A$2:$A$36,BS!C$2:C$36," ",0,1)/_xlfn.XLOOKUP($A20,BS!$A$2:$A$36,BS!D$2:D$36,"",0,1)-1, "") -> 0.037717821 | D20: =IFERROR(_xlfn.XLOOKUP($A20,BS!$A$2:$A$36,BS!D$2:D$36," ",0,1)/_xlfn.XLOOKUP($A20,BS!$A$2:$A$36,BS!E$2:E$36,"",0,1)-1, "") -> 0.038808902 | E20: =IFERROR(_xlfn.XLOOKUP($A20,BS!$A$2:$A$36,BS!E$2:E$36," ",0,1)/_xlfn.XLOOKUP($A20,BS!$A$2:$A$36,BS!F$2:F$36,"",0,1)-1, "") -> 0.0088841294
A22: II. EQUITY AND LIABILITIES
A23: (1) EQUITY
A24: Equity share capital
A25: Other equity
A26: (2) NON-CURRENT LIABILITIES
A27: Financial liabilities (Borrowings & Lease)
A28: Provisions
A29: Deferred tax liabilities (Net)
A30: Other non-current liabilities
A31: (3) CURRENT LIABILITIES
A32: Financial liabilities (Borrowings, Trade Payables, Others)
A33: Provisions
... A36: TOTAL EQUITY AND LIABILITIES (1) + (2) + (3)

Sheet ISCOMM
A1: Common -Size Income Statement of Tata Motors from FY2020 TO FY2024
A2: Particulars | B2: FY2024 | C2: FY2023 | D2: FY2022 | E2: FY2021 | F2: FY2020
A3: I. Revenue from operations
A4: (a) Revenue | B4: =_xlfn.XLOOKUP($A4,IS!$A$2:$A$27,IS!B$2:B$27,"",0,1)/_xlfn.XLOOKUP(ISCOMM!$A$4,IS!$A$2:$A$27,IS!B$2:B$27," ",0,1) -> 1 | C4: =_xlfn.XLOOKUP($A4,IS!$A$2:$A$27,IS!C$2:C$27,"",0,1)/_xlfn.XLOOKUP(ISCOMM!$A$4,IS!$A$2:$A$27,IS!C$2:C$27," ",0,1) -> 1 | D4: =_xlfn.XLOOKUP($A4,IS!$A$2:$A$27,IS!D$2:D$27,"",0,1)/_xlfn.XLOOKUP(ISCOMM!$A$4,IS!$A$2:$A$27,IS!D$2:D$27," ",0,1) -> 1 | E4: =_xlfn.XLOOKUP($A4,IS!$A$2:$A$27,IS!E$2:E$27,"",0,1)/_xlfn.XLOOKUP(ISCOMM!$A$4,IS!$A$2:$A$27,IS!E$2:E$27," ",0,1) -> 1 | F4: =_xlfn.XLOOKUP($A4,IS!$A$2:$A$27,IS!F$2:F$27,"",0,1)/_xlfn.XLOOKUP(ISCOMM!$A$4,IS!$A$2:$A$27,IS!F$2:F$27," ",0,1) -> 1
A5: (b) Other operating revenue | B5: =_xlfn.XLOOKUP($A5,IS!$A$2:$A$27,IS!B$2:B$27,"",0,1)/_xlfn.XLOOKUP(ISCOMM!$A$4,IS!$A$2:$A$27,IS!B$2:B$27," ",0,1) -> 0.0076589862 | C5: =_xlfn.XLOOKUP($A5,IS!$A$2:$A$27,IS!C$2:C$27,"",0,1)/_xlfn.XLOOKUP(ISCOMM!$A$4,IS!$A$2:$A$27,IS!C$2:C$27," ",0,1) -> 0.0070214111 | D5: =_xlfn.XLOOKUP($A5,IS!$A$2:$A$27,IS!D$2:D$27,"",0,1)/_xlfn.XLOOKUP(ISCOMM!$A$4,IS!$A$2:$A$27,IS!D$2:D$27," ",0,1) -> 0.0081634403 | E5: =_xlfn.XLOOKUP($A5,IS!$A$2:$A$27,IS!E$2:E$27,"",0,1)/_xlfn.XLOOKUP(ISCOMM!$A$4,IS!$A$2:$A$27,IS!E$2:E$27," ",0,1) -> 0.010139308 | F5: =_xlfn.XLOOKUP($A5,IS!$A$2:$A$27,IS!F$2:F$27,"",0,1)/_xlfn.XLOOKUP(ISCOMM!$A$4,IS!$A$2:$A$27,IS!F$2:F$27," ",0,1) -> 0.010173675
A6: Total revenue from operations (I) | B6: =_xlfn.XLOOKUP($A6,IS!$A$2:$A$27,IS!B$2:B$27,"",0,1)/_xlfn.XLOOKUP(ISCOMM!$A$4,IS!$A$2:$A$27,IS!B$2:B$27," ",0,1) -> 1.007659 | C6: =_xlfn.XLOOKUP($A6,IS!$A$2:$A$27,IS!C$2:C$27,"",0,1)/_xlfn.XLOOKUP(ISCOMM!$A$4,IS!$A$2:$A$27,IS!C$2:C$27," ",0,1) -> 1.0070214 | D6: =_xlfn.XLOOKUP($A6,IS!$A$2:$A$27,IS!D$2:D$27,"",0,1)/_xlfn.XLOOKUP(ISCOMM!$A$4,IS!$A$2:$A$27,IS!D$2:D$27," ",0,1) -> 1.0081634 | E6: =_xlfn.XLOOKUP($A6,IS!$A$2:$A$27,IS!E$2:E$27,"",0,1)/_xlfn.XLOOKUP(ISCOMM!$A$4,IS!$A$2:$A$27,IS!E$2:E$27," ",0,1) -> 1.0101393 | F6: =_xlfn.XLOOKUP($A6,IS!$A$2:$A$27,IS!F$2:F$27,"",0,1)/_xlfn.XLOOKUP(ISCOMM!$A$4,IS!$A$2:$A$27,IS!F$2:F$27," ",0,1) -> 1.0101737
A7: II. Other Income | B7: =_xlfn.XLOOKUP($A7,IS!$A$2:$A$27,IS!B$2:B$27,"",0,1)/_xlfn.XLOOKUP(ISCOMM!$A$4,IS!$A$2:$A$27,IS!B$2:B$27," ",0,1) -> 0.015806797 | C7: =_xlfn.XLOOKUP($A7,IS!$A$2:$A$27,IS!C$2:C$27,"",0,1)/_xlfn.XLOOKUP(ISCOMM!$A$4,IS!$A$2:$A$27,IS!C$2:C$27," ",0,1) -> 0.012572046 | D7: =_xlfn.XLOOKUP($A7,IS!$A$2:$A$27,IS!D$2:D$27,"",0,1)/_xlfn.XLOOKUP(ISCOMM!$A$4,IS!$A$2:$A$27,IS!D$2:D$27," ",0,1) -> 0.014076287 | E7: =_xlfn.XLOOKUP($A7,IS!$A$2:$A$27,IS!E$2:E$27,"",0,1)/_xlfn.XLOOKUP(ISCOMM!$A$4,IS!$A$2:$A$27,IS!E$2:E$27," ",0,1) -> 0.018105048 | F7: =_xlfn.XLOOKUP($A7,IS!$A$2:$A$27,IS!F$2:F$27,"",0,1)/_xlfn.XLOOKUP(ISCOMM!$A$4,IS!$A$2:$A$27,IS!F$2:F$27," ",0,1) -> 0.031804664
A8: III. Total Income (I+II) | B8: =_xlfn.XLOOKUP($A8,IS!$A$2:$A$27,IS!B$2:B$27,"",0,1)/_xlfn.XLOOKUP(ISCOMM!$A$4,IS!$A$2:$A$27,IS!B$2:B$27," ",0,1) -> 1.0234658 | C8: =_xlfn.XLOOKUP($A8,IS!$A$2:$A$27,IS!C$2:C$27,"",0,1)/_xlfn.XLOOKUP(ISCOMM!$A$4,IS!$A$2:$A$27,IS!C$2:C$27," ",0,1) -> 1.0195935 | D8: =_xlfn.XLOOKUP($A8,IS!$A$2:$A$27,IS!D$2:D$27,"",0,1)/_xlfn.XLOOKUP(ISCOMM!$A$4,IS!$A$2:$A$27,IS!D$2:D$27," ",0,1) -> 1.0222397 | E8: =_xlfn.XLOOKUP($A8,IS!$A$2:$A$27,IS!E$2:E$27,"",0,1)/_xlfn.XLOOKUP(ISCOMM!$A$4,IS!$A$2:$A$27,IS!E$2:E$27," ",0,1) -> 1.0282444 | F8: =_xlfn.XLOOKUP($A8,IS!$A$2:$A$27,IS!F$2:F$27,"",0,1)/_xlfn.XLOOKUP(ISCOMM!$A$4,IS!$A$2:$A$27,IS!F$2:F$27," ",0,1) -> 1.0419783
A9: IV. Expenses:
A10: (a) Cost of materials consumed | B10: =_xlfn.XLOOKUP($A10,IS!$A$2:$A$27,IS!B$2:B$27,"",0,1)/_xlfn.XLOOKUP(ISCOMM!$A$4,IS!$A$2:$A$27,IS!B$2:B$27," ",0,1) -> 0.6427478 | C10: =_xlfn.XLOOKUP($A10,IS!$A$2:$A$27,IS!C$2:C$27,"",0,1)/_xlfn.XLOOKUP(ISCOMM!$A$4,IS!$A$2:$A$27,IS!C$2:C$27," ",0,1) -> 0.64667014 | D10: =_xlfn.XLOOKUP($A10,IS!$A$2:$A$27,IS!D$2:D$27,"",0,1)/_xlfn.XLOOKUP(ISCOMM!$A$4,IS!$A$2:$A$27,IS!D$2:D$27," ",0,1) -> 0.67603358 | E10: =_xlfn.XLOOKUP($A10,IS!$A$2:$A$27,IS!E$2:E$27,"",0,1)/_xlfn.XLOOKUP(ISCOMM!$A$4,IS!$A$2:$A$27,IS!E$2:E$27," ",0,1) -> 0.61197365 | F10: =_xlfn.XLOOKUP($A10,IS!$A$2:$A$27,IS!F$2:F$27,"",0,1)/_xlfn.XLOOKUP(ISCOMM!$A$4,IS!$A$2:$A$27,IS!F$2:F$27," ",0,1) -> 0.60184874
A11: (b) Purchases of products for sale | B11: =_xlfn.XLOOKUP($A11,IS!$A$2:$A$27,IS!B$2:B$27,"",0,1)/_xlfn.XLOOKUP(ISCOMM!$A$4,IS!$A$2:$A$27,IS!B$2:B$27," ",0,1) -> 0.092198023 | C11: =_xlfn.XLOOKUP($A11,IS!$A$2:$A$27,IS!C$2:C$27,"",0,1)/_xlfn.XLOOKUP(ISCOMM!$A$4,IS!$A$2:$A$27,IS!C$2:C$27," ",0,1) -> 0.10048142 | D11: =_xlfn.XLOOKUP($A11,IS!$A$2:$A$27,IS!D$2:D$27,"",0,1)/_xlfn.XLOOKUP(ISCOMM!$A$4,IS!$A$2:$A$27,IS!D$2:D$27," ",0,1) -> 0.107293 | E11: =_xlfn.XLOOKUP($A11,IS!$A$2:$A$27,IS!E$2:E$27,"",0,1)/_xlfn.XLOOKUP(ISCOMM!$A$4,IS!$A$2:$A$27,IS!E$2:E$27," ",0,1) -> 0.16147226 | F11: =_xlfn.XLOOKUP($A11,IS!$A$2:$A$27,IS!F$2:F$27,"",0,1)/_xlfn.XLOOKUP(ISCOMM!$A$4,IS!$A$2:$A$27,IS!F$2:F$27," ",0,1) -> 0.13061701
A12: (c) Changes in Stock | B12: =_xlfn.XLOOKUP($A12,IS!$A$2:$A$27,IS!B$2:B$27,"",0,1)/_xlfn.XLOOKUP(ISCOMM!$A$4,IS!$A$2:$A$27,IS!B$2:B$27," ",0,1) -> 0.023868693 | C12: =_xlfn.XLOOKUP($A12,IS!$A$2:$A$27,IS!C$2:C$27,"",0,1)/_xlfn.XLOOKUP(ISCOMM!$A$4,IS!$A$2:$A$27,IS!C$2:C$27," ",0,1) -> 0.0074226433 | D12: =_xlfn.XLOOKUP($A12,IS!$A$2:$A$27,IS!D$2:D$27,"",0,1)/_xlfn.XLOOKUP(ISCOMM!$A$4,IS!$A$2:$A$27,IS!D$2:D$27," ",0,1) -> -0.0086147962 | E12: =_xlfn.XLOOKUP($A12,IS!$A$2:$A$27,IS!E$2:E$27,"",0,1)/_xlfn.XLOOKUP(ISCOMM!$A$4,IS!$A$2:$A$27,IS!E$2:E$27," ",0,1) -> -0.0023299274 | F12: =_xlfn.XLOOKUP($A12,IS!$A$2:$A$27,IS!F$2:F$27,"",0,1)/_xlfn.XLOOKUP(ISCOMM!$A$4,IS!$A$2:$A$27,IS!F$2:F$27," ",0,1) -> 0.016618774
A13: (d) Employee benefits expense | B13: =_xlfn.XLOOKUP($A13,IS!$A$2:$A$27,IS!B$2:B$27,"",0,1)/_xlfn.XLOOKUP(ISCOMM!$A$4,IS!$A$2:$A$27,IS!B$2:B$27," ",0,1) -> 0.059221878 | C13: =_xlfn.XLOOKUP($A13,IS!$A$2:$A$27,IS!C$2:C$27,"",0,1)/_xlfn.XLOOKUP(ISCOMM!$A$4,IS!$A$2:$A$27,IS!C$2:C$27," ",0,1) -> 0.061588077 | D13: =_xlfn.XLOOKUP($A13,IS!$A$2:$A$27,IS!D$2:D$27,"",0,1)/_xlfn.XLOOKUP(ISCOMM!$A$4,IS!$A$2:$A$27,IS!D$2:D$27," ",0,1) -> 0.076822429 | E13: =_xlfn.XLOOKUP($A13,IS!$A$2:$A$27,IS!E$2:E$27,"",0,1)/_xlfn.XLOOKUP(ISCOMM!$A$4,IS!$A$2:$A$27,IS!E$2:E$27," ",0,1) -> 0.085648029 | F13: =_xlfn.XLOOKUP($A13,IS!$A$2:$A$27,IS!F$2:F$27,"",0,1)/_xlfn.XLOOKUP(ISCOMM!$A$4,IS!$A$2:$A$27,IS!F$2:F$27," ",0,1) -> 0.10082174
A14: (e) Finance costs | B14: =_xlfn.XLOOKUP($A14,IS!$A$2:$A$27,IS!B$2:B$27,"",0,1)/_xlfn.XLOOKUP(ISCOMM!$A$4,IS!$A$2:$A$27,IS!B$2:B$27," ",0,1) -> 0.023447913 | C14: =_xlfn.XLOOKUP($A14,IS!$A$2:$A$27,IS!C$2:C$27,"",0,1)/_xlfn.XLOOKUP(ISCOMM!$A$4,IS!$A$2:$A$27,IS!C$2:C$27," ",0,1) -> 0.031355993 | D14: =_xlfn.XLOOKUP($A14,IS!$A$2:$A$27,IS!D$2:D$27,"",0,1)/_xlfn.XLOOKUP(ISCOMM!$A$4,IS!$A$2:$A$27,IS!D$2:D$27," ",0,1) -> 0.045257809 | E14: =_xlfn.XLOOKUP($A14,IS!$A$2:$A$27,IS!E$2:E$27,"",0,1)/_xlfn.XLOOKUP(ISCOMM!$A$4,IS!$A$2:$A$27,IS!E$2:E$27," ",0,1) -> 0.049154639 | F14: =_xlfn.XLOOKUP($A14,IS!$A$2:$A$27,IS!F$2:F$27,"",0,1)/_xlfn.XLOOKUP(ISCOMM!$A$4,IS!$A$2:$A$27,IS!F$2:F$27," ",0,1) -> 0.045371174
A15: (f) Foreign exchange loss (net) | B15: =_xlfn.XLOOKUP($A15,IS!$A$2:$A$27,IS!B$2:B$27,"",0,1)/_xlfn.XLOOKUP(ISCOMM!$A$4,IS!$A$2:$A$27,IS!B$2:B$27," ",0,1) -> 0.0027591925 | C15: =_xlfn.XLOOKUP($A15,IS!$A$2:$A$27,IS!C$2:C$27,"",0,1)/_xlfn.XLOOKUP(ISCOMM!$A$4,IS!$A$2:$A$27,IS!C$2:C$27," ",0,1) -> 0.0042843028 | D15: =_xlfn.XLOOKUP($A15,IS!$A$2:$A$27,IS!D$2:D$27,"",0,1)/_xlfn.XLOOKUP(ISCOMM!$A$4,IS!$A$2:$A$27,IS!D$2:D$27," ",0,1) -> 0.0029182417 | E15: =_xlfn.XLOOKUP($A15,IS!$A$2:$A$27,IS!E$2:E$27,"",0,1)/_xlfn.XLOOKUP(ISCOMM!$A$4,IS!$A$2:$A$27,IS!E$2:E$27," ",0,1) -> 0.00062328995 | F15: =_xlfn.XLOOKUP($A15,IS!$A$2:$A$27,IS!F$2:F$27,"",0,1)/_xlfn.XLOOKUP(ISCOMM!$A$4,IS!$A$2:$A$27,IS!F$2:F$27," ",0,1) -> 0.005496052
A16: (g) Depreciation and amortisation expense | B16: =_xlfn.XLOOKUP($A16,IS!$A$2:$A$27,IS!B$2:B$27,"",0,1)/_xlfn.XLOOKUP(ISCOMM!$A$4,IS!$A$2:$A$27,IS!B$2:B$27," ",0,1) -> 0.027724441 | C16: =_xlfn.XLOOKUP($A16,IS!$A$2:$A$27,IS!C$2:C$27,"",0,1)/_xlfn.XLOOKUP(ISCOMM!$A$4,IS!$A$2:$A$27,IS!C$2:C$27," ",0,1) -> 0.027058061 | D16: =_xlfn.XLOOKUP($A16,IS!$A$2:$A$27,IS!D$2:D$27,"",0,1)/_xlfn.XLOOKUP(ISCOMM!$A$4,IS!$A$2:$A$27,IS!D$2:D$27," ",0,1) -> 0.037554044 | E16: =_xlfn.XLOOKUP($A16,IS!$A$2:$A$27,IS!E$2:E$27,"",0,1)/_xlfn.XLOOKUP(ISCOMM!$A$4,IS!$A$2:$A$27,IS!E$2:E$27," ",0,1) -> 0.071431348 | F16: =_xlfn.XLOOKUP($A16,IS!$A$2:$A$27,IS!F$2:F$27,"",0,1)/_xlfn.XLOOKUP(ISCOMM!$A$4,IS!$A$2:$A$27,IS!F$2:F$27," ",0,1) -> 0.077618282
A17: (h) Product development/Engineering expenses | B17: =_xlfn.XLOOKUP($A17,IS!$A$2:$A$27,IS!B$2:B$27,"",0,1)/_xlfn.XLOOKUP(ISCOMM!$A$4,IS!$A$2:$A$27,IS!B$2:B$27," ",0,1) -> 0.015186969 | C17: =_xlfn.XLOOKUP($A17,IS!$A$2:$A$27,IS!C$2:C$27,"",0,1)/_xlfn.XLOOKUP(ISCOMM!$A$4,IS!$A$2:$A$27,IS!C$2:C$27," ",0,1) -> 0.013768392 | D17: =_xlfn.XLOOKUP($A17,IS!$A$2:$A$27,IS!D$2:D$27,"",0,1)/_xlfn.XLOOKUP(ISCOMM!$A$4,IS!$A$2:$A$27,IS!D$2:D$27," ",0,1) -> 0.012668253 | E17: =_xlfn.XLOOKUP($A17,IS!$A$2:$A$27,IS!E$2:E$27,"",0,1)/_xlfn.XLOOKUP(ISCOMM!$A$4,IS!$A$2:$A$27,IS!E$2:E$27," ",0,1) -> 0.019489946 | F17: =_xlfn.XLOOKUP($A17,IS!$A$2:$A$27,IS!F$2:F$27,"",0,1)/_xlfn.XLOOKUP(ISCOMM!$A$4,IS!$A$2:$A$27,IS!F$2:F$27," ",0,1) -> 0.019092227
A18: (i) Other expenses | B18: =_xlfn.XLOOKUP($A18,IS!$A$2:$A$27,IS!B$2:B$27,"",0,1)/_xlfn.XLOOKUP(ISCOMM!$A$4,IS!$A$2:$A$27,IS!B$2:B$27," ",0,1) -> 0.10461274 | C18: =_xlfn.XLOOKUP($A18,IS!$A$2:$A$27,IS!C$2:C$27,"",0,1)/_xlfn.XLOOKUP(ISCOMM!$A$4,IS!$A$2:$A$27,IS!C$2:C$27," ",0,1) -> 0.11975312 | D18: =_xlfn.XLOOKUP($A18,IS!$A$2:$A$27,IS!D$2:D$27,"",0,1)/_xlfn.XLOOKUP(ISCOMM!$A$4,IS!$A$2:$A$27,IS!D$2:D$27," ",0,1) -> 0.1283828 | E18: =_xlfn.XLOOKUP($A18,IS!$A$2:$A$27,IS!E$2:E$27,"",0,1)/_xlfn.XLOOKUP(ISCOMM!$A$4,IS!$A$2:$A$27,IS!E$2:E$27," ",0,1) -> 0.12054453 | F18: =_xlfn.XLOOKUP($A18,IS!$A$2:$A$27,IS!F$2:F$27,"",0,1)/_xlfn.XLOOKUP(ISCOMM!$A$4,IS!$A$2:$A$27,IS!F$2:F$27," ",0,1) -> 0.17754663
A19: (j) Amount transferred to capital and other accounts | B19: =_xlfn.XLOOKUP($A19,IS!$A$2:$A$27,IS!B$2:B$27,"",0,1)/_xlfn.XLOOKUP(ISCOMM!$A$4,IS!$A$2:$A$27,IS!B$2:B$27," ",0,1) -> -0.015529806 | C19: =_xlfn.XLOOKUP($A19,IS!$A$2:$A$27,IS!C$2:C$27,"",0,1)/_xlfn.XLOOKUP(ISCOMM!$A$4,IS!$A$2:$A$27,IS!C$2:C$27," ",0,1) -> -0.016336125 | D19: =_xlfn.XLOOKUP($A19,IS!$A$2:$A$27,IS!D$2:D$27,"",0,1)/_xlfn.XLOOKUP(ISCOMM!$A$4,IS!$A$2:$A$27,IS!D$2:D$27," ",0,1) -> -0.019313167 | E19: =_xlfn.XLOOKUP($A19,IS!$A$2:$A$27,IS!E$2:E$27,"",0,1)/_xlfn.XLOOKUP(ISCOMM!$A$4,IS!$A$2:$A$27,IS!E$2:E$27," ",0,1) -> -0.017558864 | F19: =_xlfn.XLOOKUP($A19,IS!$A$2:$A$27,IS!F$2:F$27,"",0,1)/_xlfn.XLOOKUP(ISCOMM!$A$4,IS!$A$2:$A$27,IS!F$2:F$27," ",0,1) -> -0.026892942
A20: Total Expenses (IV) | B20: =_xlfn.XLOOKUP($A20,IS!$A$2:$A$27,IS!B$2:B$27,"",0,1)/_xlfn.XLOOKUP(ISCOMM!$A$4,IS!$A$2:$A$27,IS!B$2:B$27," ",0,1) -> 0.95286883 | C20: =_xlfn.XLOOKUP($A20,IS!$A$2:$A$27,IS!C$2:C$27,"",0,1)/_xlfn.XLOOKUP(ISCOMM!$A$4,IS!$A$2:$A$27,IS!C$2:C$27," ",0,1) -> 0.99604602 | D20: =_xlfn.XLOOKUP($A20,IS!$A$2:$A$27,IS!D$2:D$27,"",0,1)/_xlfn.XLOOKUP(ISCOMM!$A$4,IS!$A$2:$A$27,IS!D$2:D$27," ",0,1) -> 1.0590022 | E20: =_xlfn.XLOOKUP($A20,IS!$A$2:$A$27,IS!E$2:E$27,"",0,1)/_xlfn.XLOOKUP(ISCOMM!$A$4,IS!$A$2:$A$27,IS!E$2:E$27," ",0,1) -> 1.1005166 | F20: =_xlfn.XLOOKUP($A20,IS!$A$2:$A$27,IS!F$2:F$27,"",0,1)/_xlfn.XLOOKUP(ISCOMM!$A$4,IS!$A$2:$A$27,IS!F$2:F$27," ",0,1) -> 1.1481377
A21: V. Profit/(Loss) before exceptional items and tax (III-IV) | B21: =_xlfn.XLOOKUP($A21,IS!$A$2:$A$27,IS!B$2:B$27,"",0,1)/_xlfn.XLOOKUP(ISCOMM!$A$4,IS!$A$2:$A$27,IS!B$2:B$27," ",0,1) -> 0.070596949 | C21: =_xlfn.XLOOKUP($A21,IS!$A$2:$A$27,IS!C$2:C$27,"",0,1)/_xlfn.XLOOKUP(ISCOMM!$A$4,IS!$A$2:$A$27,IS!C$2:C$27," ",0,1) -> 0.023547432 | D21: =_xlfn.XLOOKUP($A21,IS!$A$2:$A$27,IS!D$2:D$27,"",0,1)/_xlfn.XLOOKUP(ISCOMM!$A$4,IS!$A$2:$A$27,IS!D$2:D$27," ",0,1) -> -0.036762465 | E21: =_xlfn.XLOOKUP($A21,IS!$A$2:$A$27,IS!E$2:E$27,"",0,1)/_xlfn.XLOOKUP(ISCOMM!$A$4,IS!$A$2:$A$27,IS!E$2:E$27," ",0,1) -> -0.07227221 | F21: =_xlfn.XLOOKUP($A21,IS!$A$2:$A$27,IS!F$2:F$27,"",0,1)/_xlfn.XLOOKUP(ISCOMM!$A$4,IS!$A$2:$A$27,IS!F$2:F$27," ",0,1) -> -0.10615935
... A27: XI. Total comprehensive income/(loss) for the year | B27: =_xlfn.XLOOKUP($A27,IS!$A$2:$A$27,IS!B$2:B$27,"",0,1)/_xlfn.XLOOKUP(ISCOMM!$A$4,IS!$A$2:$A$27,IS!B$2:B$27," ",0,1) -> 0.11462691 | C27: =_xlfn.XLOOKUP($A27,IS!$A$2:$A$27,IS!C$2:C$27,"",0,1)/_xlfn.XLOOKUP(ISCOMM!$A$4,IS!$A$2:$A$27,IS!C$2:C$27," ",0,1) -> 0.037544924 | D27: =_xlfn.XLOOKUP($A27,IS!$A$2:$A$27,IS!D$2:D$27,"",0,1)/_xlfn.XLOOKUP(ISCOMM!$A$4,IS!$A$2:$A$27,IS!D$2:D$27," ",0,1) -> -0.027029731 | E27: =_xlfn.XLOOKUP($A27,IS!$A$2:$A$27,IS!E$2:E$27,"",0,1)/_xlfn.XLOOKUP(ISCOMM!$A$4,IS!$A$2:$A$27,IS!E$2:E$27," ",0,1) -> -0.041934613 | F27: =_xlfn.XLOOKUP($A27,IS!$A$2:$A$27,IS!F$2:F$27,"",0,1)/_xlfn.XLOOKUP(ISCOMM!$A$4,IS!$A$2:$A$27,IS!F$2:F$27," ",0,1) -> -0.17634163

Sheet BS_COMM
A1: Comparative Balance Sheet of Tata Motors from FY2020 TO FY2024
A2: Particulars | B2: FY2024 | C2: FY2023 | D2: FY2022 | E2: FY2021 | F2: FY2020
A3: I. ASSETS
A4: (1) NON-CURRENT ASSETS
A5: Property, plant and equipment (PPE) | B5: =_xlfn.XLOOKUP($A5,BS!$A$2:$A$36,BS!B$2:B$36," ",0,1)/_xlfn.XLOOKUP(BS_COMM!$A$20,BS!$A$2:$A$36,BS!B$2:B$36," ",0,1) -> 0.16654151 | C5: =_xlfn.XLOOKUP($A5,BS!$A$2:$A$36,BS!C$2:C$36," ",0,1)/_xlfn.XLOOKUP(BS_COMM!$A$20,BS!$A$2:$A$36,BS!C$2:C$36," ",0,1) -> 0.20318312 | D5: =_xlfn.XLOOKUP($A5,BS!$A$2:$A$36,BS!D$2:D$36," ",0,1)/_xlfn.XLOOKUP(BS_COMM!$A$20,BS!$A$2:$A$36,BS!D$2:D$36," ",0,1) -> 0.20451646 | E5: =_xlfn.XLOOKUP($A5,BS!$A$2:$A$36,BS!E$2:E$36," ",0,1)/_xlfn.XLOOKUP(BS_COMM!$A$20,BS!$A$2:$A$36,BS!E$2:E$36," ",0,1) -> 0.3083645 | F5: =_xlfn.XLOOKUP($A5,BS!$A$2:$A$36,BS!F$2:F$36," ",0,1)/_xlfn.XLOOKUP(BS_COMM!$A$20,BS!$A$2:$A$36,BS!F$2:F$36," ",0,1) -> 0.34245628
A6: Capital work-in-progress (CWIP) | B6: =_xlfn.XLOOKUP($A6,BS!$A$2:$A$36,BS!B$2:B$36," ",0,1)/_xlfn.XLOOKUP(BS_COMM!$A$20,BS!$A$2:$A$36,BS!B$2:B$36," ",0,1) -> 0.0079518675 | C6: =_xlfn.XLOOKUP($A6,BS!$A$2:$A$36,BS!C$2:C$36," ",0,1)/_xlfn.XLOOKUP(BS_COMM!$A$20,BS!$A$2:$A$36,BS!C$2:C$36," ",0,1) -> 0.0096055028 | D6: =_xlfn.XLOOKUP($A6,BS!$A$2:$A$36,BS!D$2:D$36," ",0,1)/_xlfn.XLOOKUP(BS_COMM!$A$20,BS!$A$2:$A$36,BS!D$2:D$36," ",0,1) -> 0.01013334 | E6: =_xlfn.XLOOKUP($A6,BS!$A$2:$A$36,BS!E$2:E$36," ",0,1)/_xlfn.XLOOKUP(BS_COMM!$A$20,BS!$A$2:$A$36,BS!E$2:E$36," ",0,1) -> 0.023819541 | F6: =_xlfn.XLOOKUP($A6,BS!$A$2:$A$36,BS!F$2:F$36," ",0,1)/_xlfn.XLOOKUP(BS_COMM!$A$20,BS!$A$2:$A$36,BS!F$2:F$36," ",0,1) -> 0.031858192
A7: Right of use assets (ROU) | B7: =_xlfn.XLOOKUP($A7,BS!$A$2:$A$36,BS!B$2:B$36," ",0,1)/_xlfn.XLOOKUP(BS_COMM!$A$20,BS!$A$2:$A$36,BS!B$2:B$36," ",0,1) -> 0.0046724905 | C7: =_xlfn.XLOOKUP($A7,BS!$A$2:$A$36,BS!C$2:C$36," ",0,1)/_xlfn.XLOOKUP(BS_COMM!$A$20,BS!$A$2:$A$36,BS!C$2:C$36," ",0,1) -> 0.0057434449 | D7: =_xlfn.XLOOKUP($A7,BS!$A$2:$A$36,BS!D$2:D$36," ",0,1)/_xlfn.XLOOKUP(BS_COMM!$A$20,BS!$A$2:$A$36,BS!D$2:D$36," ",0,1) -> 0.0057566153 | E7: =_xlfn.XLOOKUP($A7,BS!$A$2:$A$36,BS!E$2:E$36," ",0,1)/_xlfn.XLOOKUP(BS_COMM!$A$20,BS!$A$2:$A$36,BS!E$2:E$36," ",0,1) -> 0.017618629 | F7: =_xlfn.XLOOKUP($A7,BS!$A$2:$A$36,BS!F$2:F$36," ",0,1)/_xlfn.XLOOKUP(BS_COMM!$A$20,BS!$A$2:$A$36,BS!F$2:F$36," ",0,1) -> 0.012151231
A8: Goodwill | B8: =_xlfn.XLOOKUP($A8,BS!$A$2:$A$36,BS!B$2:B$36," ",0,1)/_xlfn.XLOOKUP(BS_COMM!$A$20,BS!$A$2:$A$36,BS!B$2:B$36," ",0,1) -> 0.0013688014 | C8: =_xlfn.XLOOKUP($A8,BS!$A$2:$A$36,BS!C$2:C$36," ",0,1)/_xlfn.XLOOKUP(BS_COMM!$A$20,BS!$A$2:$A$36,BS!C$2:C$36," ",0,1) -> 0.0016534513 | D8: =_xlfn.XLOOKUP($A8,BS!$A$2:$A$36,BS!D$2:D$36," ",0,1)/_xlfn.XLOOKUP(BS_COMM!$A$20,BS!$A$2:$A$36,BS!D$2:D$36," ",0,1) -> 0.0017158159 | E8: =_xlfn.XLOOKUP($A8,BS!$A$2:$A$36,BS!E$2:E$36," ",0,1)/_xlfn.XLOOKUP(BS_COMM!$A$20,BS!$A$2:$A$36,BS!E$2:E$36," ",0,1) -> 0.0017824049 | F8: =_xlfn.XLOOKUP($A8,BS!$A$2:$A$36,BS!F$2:F$36," ",0,1)/_xlfn.XLOOKUP(BS_COMM!$A$20,BS!$A$2:$A$36,BS!F$2:F$36," ",0,1) -> 0.00179824
A9: Other intangible assets | B9: =_xlfn.XLOOKUP($A9,BS!$A$2:$A$36,BS!B$2:B$36," ",0,1)/_xlfn.XLOOKUP(BS_COMM!$A$20,BS!$A$2:$A$36,BS!B$2:B$36," ",0,1) -> 0.024429424 | C9: =_xlfn.XLOOKUP($A9,BS!$A$2:$A$36,BS!C$2:C$36," ",0,1)/_xlfn.XLOOKUP(BS_COMM!$A$20,BS!$A$2:$A$36,BS!C$2:C$36," ",0,1) -> 0.031950373 | D9: =_xlfn.XLOOKUP($A9,BS!$A$2:$A$36,BS!D$2:D$36," ",0,1)/_xlfn.XLOOKUP(BS_COMM!$A$20,BS!$A$2:$A$36,BS!D$2:D$36," ",0,1) -> 0.034802371 | E9: =_xlfn.XLOOKUP($A9,BS!$A$2:$A$36,BS!E$2:E$36," ",0,1)/_xlfn.XLOOKUP(BS_COMM!$A$20,BS!$A$2:$A$36,BS!E$2:E$36," ",0,1) -> 0.11074258 | F9: =_xlfn.XLOOKUP($A9,BS!$A$2:$A$36,BS!F$2:F$36," ",0,1)/_xlfn.XLOOKUP(BS_COMM!$A$20,BS!$A$2:$A$36,BS!F$2:F$36," ",0,1) -> 0.10105713
A10: Intangible assets under development | B10: =_xlfn.XLOOKUP($A10,BS!$A$2:$A$36,BS!B$2:B$36," ",0,1)/_xlfn.XLOOKUP(BS_COMM!$A$20,BS!$A$2:$A$36,BS!B$2:B$36," ",0,1) -> 0.0070353272 | C10: =_xlfn.XLOOKUP($A10,BS!$A$2:$A$36,BS!C$2:C$36," ",0,1)/_xlfn.XLOOKUP(BS_COMM!$A$20,BS!$A$2:$A$36,BS!C$2:C$36," ",0,1) -> 0.0084983628 | D10: =_xlfn.XLOOKUP($A10,BS!$A$2:$A$36,BS!D$2:D$36," ",0,1)/_xlfn.XLOOKUP(BS_COMM!$A$20,BS!$A$2:$A$36,BS!D$2:D$36," ",0,1) -> 0.015272996 | E10: =_xlfn.XLOOKUP($A10,BS!$A$2:$A$36,BS!E$2:E$36," ",0,1)/_xlfn.XLOOKUP(BS_COMM!$A$20,BS!$A$2:$A$36,BS!E$2:E$36," ",0,1) -> 0.028856467 | F10: =_xlfn.XLOOKUP($A10,BS!$A$2:$A$36,BS!F$2:F$36," ",0,1)/_xlfn.XLOOKUP(BS_COMM!$A$20,BS!$A$2:$A$36,BS!F$2:F$36," ",0,1) -> 0.049711381
A11: Investments in subsidiaries, JVs & associates | B11: =_xlfn.XLOOKUP($A11,BS!$A$2:$A$36,BS!B$2:B$36," ",0,1)/_xlfn.XLOOKUP(BS_COMM!$A$20,BS!$A$2:$A$36,BS!B$2:B$36," ",0,1) -> 0.35666111 | C11: =_xlfn.XLOOKUP($A11,BS!$A$2:$A$36,BS!C$2:C$36," ",0,1)/_xlfn.XLOOKUP(BS_COMM!$A$20,BS!$A$2:$A$36,BS!C$2:C$36," ",0,1) -> 0.46683094 | D11: =_xlfn.XLOOKUP($A11,BS!$A$2:$A$36,BS!D$2:D$36," ",0,1)/_xlfn.XLOOKUP(BS_COMM!$A$20,BS!$A$2:$A$36,BS!D$2:D$36," ",0,1) -> 0.42810274 | E11: =_xlfn.XLOOKUP($A11,BS!$A$2:$A$36,BS!E$2:E$36," ",0,1)/_xlfn.XLOOKUP(BS_COMM!$A$20,BS!$A$2:$A$36,BS!E$2:E$36," ",0,1) -> 0.25700519 | F11: =_xlfn.XLOOKUP($A11,BS!$A$2:$A$36,BS!F$2:F$36," ",0,1)/_xlfn.XLOOKUP(BS_COMM!$A$20,BS!$A$2:$A$36,BS!F$2:F$36," ",0,1) -> 0.27552125
A12: Financial assets (Investments, Loans, Others) | B12: =_xlfn.XLOOKUP($A12,BS!$A$2:$A$36,BS!B$2:B$36," ",0,1)/_xlfn.XLOOKUP(BS_COMM!$A$20,BS!$A$2:$A$36,BS!B$2:B$36," ",0,1) -> -0.017729494 | C12: =_xlfn.XLOOKUP($A12,BS!$A$2:$A$36,BS!C$2:C$36," ",0,1)/_xlfn.XLOOKUP(BS_COMM!$A$20,BS!$A$2:$A$36,BS!C$2:C$36," ",0,1) -> -0.023396946 | D12: =_xlfn.XLOOKUP($A12,BS!$A$2:$A$36,BS!D$2:D$36," ",0,1)/_xlfn.XLOOKUP(BS_COMM!$A$20,BS!$A$2:$A$36,BS!D$2:D$36," ",0,1) -> -0.026104679 | E12: =_xlfn.XLOOKUP($A12,BS!$A$2:$A$36,BS!E$2:E$36," ",0,1)/_xlfn.XLOOKUP(BS_COMM!$A$20,BS!$A$2:$A$36,BS!E$2:E$36," ",0,1) -> 0.030417443 | F12: =_xlfn.XLOOKUP($A12,BS!$A$2:$A$36,BS!F$2:F$36," ",0,1)/_xlfn.XLOOKUP(BS_COMM!$A$20,BS!$A$2:$A$36,BS!F$2:F$36," ",0,1) -> 0.040006802
A13: Non-current tax assets (Net) | B13: =_xlfn.XLOOKUP($A13,BS!$A$2:$A$36,BS!B$2:B$36," ",0,1)/_xlfn.XLOOKUP(BS_COMM!$A$20,BS!$A$2:$A$36,BS!B$2:B$36," ",0,1) -> 0.024194453 | C13: =_xlfn.XLOOKUP($A13,BS!$A$2:$A$36,BS!C$2:C$36," ",0,1)/_xlfn.XLOOKUP(BS_COMM!$A$20,BS!$A$2:$A$36,BS!C$2:C$36," ",0,1) -> 0.031867609 | D13: =_xlfn.XLOOKUP($A13,BS!$A$2:$A$36,BS!D$2:D$36," ",0,1)/_xlfn.XLOOKUP(BS_COMM!$A$20,BS!$A$2:$A$36,BS!D$2:D$36," ",0,1) -> 0.031984928 | E13: =_xlfn.XLOOKUP($A13,BS!$A$2:$A$36,BS!E$2:E$36," ",0,1)/_xlfn.XLOOKUP(BS_COMM!$A$20,BS!$A$2:$A$36,BS!E$2:E$36," ",0,1) -> 0.013329273 | F13: =_xlfn.XLOOKUP($A13,BS!$A$2:$A$36,BS!F$2:F$36," ",0,1)/_xlfn.XLOOKUP(BS_COMM!$A$20,BS!$A$2:$A$36,BS!F$2:F$36," ",0,1) -> 0.013210866
A14: Other non-current assets | B14: =_xlfn.XLOOKUP($A14,BS!$A$2:$A$36,BS!B$2:B$36," ",0,1)/_xlfn.XLOOKUP(BS_COMM!$A$20,BS!$A$2:$A$36,BS!B$2:B$36," ",0,1) -> -0.017985186 | C14: =_xlfn.XLOOKUP($A14,BS!$A$2:$A$36,BS!C$2:C$36," ",0,1)/_xlfn.XLOOKUP(BS_COMM!$A$20,BS!$A$2:$A$36,BS!C$2:C$36," ",0,1) -> -0.024018679 | D14: =_xlfn.XLOOKUP($A14,BS!$A$2:$A$36,BS!D$2:D$36," ",0,1)/_xlfn.XLOOKUP(BS_COMM!$A$20,BS!$A$2:$A$36,BS!D$2:D$36," ",0,1) -> -0.035660885 | E14: =_xlfn.XLOOKUP($A14,BS!$A$2:$A$36,BS!E$2:E$36," ",0,1)/_xlfn.XLOOKUP(BS_COMM!$A$20,BS!$A$2:$A$36,BS!E$2:E$36," ",0,1) -> 0.019008901 | F14: =_xlfn.XLOOKUP($A14,BS!$A$2:$A$36,BS!F$2:F$36," ",0,1)/_xlfn.XLOOKUP(BS_COMM!$A$20,BS!$A$2:$A$36,BS!F$2:F$36," ",0,1) -> 0.021923683
A15: (2) CURRENT ASSETS | B15: =_xlfn.XLOOKUP($A15,BS!$A$2:$A$36,BS!B$2:B$36," ",0,1)/_xlfn.XLOOKUP(BS_COMM!$A$20,BS!$A$2:$A$36,BS!B$2:B$36," ",0,1) -> 0.50086764 | C15: =_xlfn.XLOOKUP($A15,BS!$A$2:$A$36,BS!C$2:C$36," ",0,1)/_xlfn.XLOOKUP(BS_COMM!$A$20,BS!$A$2:$A$36,BS!C$2:C$36," ",0,1) -> 0.44834529 | D15: =_xlfn.XLOOKUP($A15,BS!$A$2:$A$36,BS!D$2:D$36," ",0,1)/_xlfn.XLOOKUP(BS_COMM!$A$20,BS!$A$2:$A$36,BS!D$2:D$36," ",0,1) -> 0.46392536 | E15: =_xlfn.XLOOKUP($A15,BS!$A$2:$A$36,BS!E$2:E$36," ",0,1)/_xlfn.XLOOKUP(BS_COMM!$A$20,BS!$A$2:$A$36,BS!E$2:E$36," ",0,1) -> 0.45526567 | F15: =_xlfn.XLOOKUP($A15,BS!$A$2:$A$36,BS!F$2:F$36," ",0,1)/_xlfn.XLOOKUP(BS_COMM!$A$20,BS!$A$2:$A$36,BS!F$2:F$36," ",0,1) -> 0.14267271
A16: Inventories | B16: =_xlfn.XLOOKUP($A16,BS!$A$2:$A$36,BS!B$2:B$36," ",0,1)/_xlfn.XLOOKUP(BS_COMM!$A$20,BS!$A$2:$A$36,BS!B$2:B$36," ",0,1) -> 0.11393252 | C16: =_xlfn.XLOOKUP($A16,BS!$A$2:$A$36,BS!C$2:C$36," ",0,1)/_xlfn.XLOOKUP(BS_COMM!$A$20,BS!$A$2:$A$36,BS!C$2:C$36," ",0,1) -> 0.092028943 | D16: =_xlfn.XLOOKUP($A16,BS!$A$2:$A$36,BS!D$2:D$36," ",0,1)/_xlfn.XLOOKUP(BS_COMM!$A$20,BS!$A$2:$A$36,BS!D$2:D$36," ",0,1) -> 0.092619775 | E16: =_xlfn.XLOOKUP($A16,BS!$A$2:$A$36,BS!E$2:E$36," ",0,1)/_xlfn.XLOOKUP(BS_COMM!$A$20,BS!$A$2:$A$36,BS!E$2:E$36," ",0,1) -> 0.091462247 | F16: =_xlfn.XLOOKUP($A16,BS!$A$2:$A$36,BS!F$2:F$36," ",0,1)/_xlfn.XLOOKUP(BS_COMM!$A$20,BS!$A$2:$A$36,BS!F$2:F$36," ",0,1) -> 0.1207699
... A20: TOTAL ASSETS (1) + (2) | B20: =_xlfn.XLOOKUP($A20,BS!$A$2:$A$36,BS!B$2:B$36," ",0,1)/_xlfn.XLOOKUP(BS_COMM!$A$20,BS!$A$2:$A$36,BS!B$2:B$36," ",0,1) -> 1 | C20: =_xlfn.XLOOKUP($A20,BS!$A$2:$A$36,BS!C$2:C$36," ",0,1)/_xlfn.XLOOKUP(BS_COMM!$A$20,BS!$A$2:$A$36,BS!C$2:C$36," ",0,1) -> 1 | D20: =_xlfn.XLOOKUP($A20,BS!$A$2:$A$36,BS!D$2:D$36," ",0,1)/_xlfn.XLOOKUP(BS_COMM!$A$20,BS!$A$2:$A$36,BS!D$2:D$36," ",0,1) -> 1 | E20: =_xlfn.XLOOKUP($A20,BS!$A$2:$A$36,BS!E$2:E$36," ",0,1)/_xlfn.XLOOKUP(BS_COMM!$A$20,BS!$A$2:$A$36,BS!E$2:E$36," ",0,1) -> 1 | F20: =_xlfn.XLOOKUP($A20,BS!$A$2:$A$36,BS!F$2:F$36," ",0,1)/_xlfn.XLOOKUP(BS_COMM!$A$20,BS!$A$2:$A$36,BS!F$2:F$36," ",0,1) -> 1
A22: II. EQUITY AND LIABILITIES
A23: (1) EQUITY
A24: Equity share capital
A25: Other equity
A26: (2) NON-CURRENT LIABILITIES
A27: Financial liabilities (Borrowings & Lease)
A28: Provisions
A29: Deferred tax liabilities (Net)
A30: Other non-current liabilities
A31: (3) CURRENT LIABILITIES
A32: Financial liabilities (Borrowings, Trade Payables, Others)
A33: Provisions
... A36: TOTAL EQUITY AND LIABILITIES (1) + (2) + (3)
